Workbook

Sheet 頁面設定
A1: 分頁ID | B1: 分頁標題 | C1: 頁首圖URL | D1: 頁首大標題 | E1: 頁首副標題 | F1: 版面類型 | G1: 資料工作頁 | H1: 說明文字 | I1: 排列順序 | J1: 啟用
A2: news | B2: 所有公告 | D2: 所有公告 | E2: All Announcements | F2: news | G2: 公告總庫 | I2: 1 | J2: TRUE

Sheet 使用說明
A1: 📖 公告總庫使用說明
A3: 一、本檔內容
A4: 「公告總庫」工作頁收錄系網 2012-03 ~ 2026-05-26 全部公告（已發布），分類為站方 WordPress 官方主分類。本檔由使用者上傳版本單次轉換而成，資料值原樣保留。
A6: 二、欄位說明（資料自第 4 列起）
A7: A 顯示（TRUE/FALSE：設 FALSE 該則不在網頁顯示，預設 TRUE）｜B 分類（官方主分類）｜C 次分類（主分類以外的官方分類，頓號分隔多值）｜D 刊登日期｜E 標題｜F 內文純文字（3,000 字截斷）｜G–L 連結 1–3 的名稱與網址｜M 原始公告頁連結｜N 發布者。
A9: 三、分類統計工作頁
A10: 四組統計皆以公式連動「公告總庫」：①八大分類 × 月份 ②八大分類 × 年度 ③發布者 × 主分類 ④發布者 × 年度。高中生* 列為主＋次分類合計，置於總計之外、不重複加總。統計計入全部資料列，不受 A 欄「顯示」影響。
A12: 四、搭配公告總庫.html 使用
A13: 以瀏覽器開啟 HTML 後選擇本檔即可瀏覽、搜尋、複製公告；A 欄設 FALSE 的公告不會出現在網頁清單、頁籤計數與 📊 分析中。掛有次分類的公告會同時出現在主分類與次分類頁籤。HTML 全部欄位依表頭名稱定位，調整欄位順序不影響網頁。

Sheet 公告總庫
A1: 🗄 公告總庫（2012–2026 全部公告，官方分類，新→舊）
A2: A 顯示（FALSE=網頁不顯示，預設 TRUE）／B 分類／C 次分類（頓號分隔多值）／N 發布者。
A3: 顯示 | B3: 分類 | C3: 次分類 | D3: 刊登日期 | E3: 標題 | F3: 內文(純文字) | G3: 連結1名稱 | H3: 連結1網址 | I3: 連結2名稱 | J3: 連結2網址 | K3: 連結3名稱 | L3: 連結3網址 | M3: 原始連結 | N3: 發布者
A6: TRUE | B6: 獎學金 | D6: 46178 | E6: NIMS Internship Program | F6: Provide undergraduate and graduate students with technical experience of cutting-edge research activities in the field of materials and science | H6: https://www.nims.go.jp/eng/hr-development/internship.html | N6: 許慧君
A7: TRUE | B7: 獎學金 | D7: 46175 | E7: 教育部114學年度「大專校院學生雙語化學習計畫」出國補助申請審核結果公告(第二梯次) | F7: 恭喜以下同學獲獎 請獲補助同學留意Email通知，內有經費補助重要訊息。 博士班 113282005 張容誌 博士班 114282001 潘勤華 學士班 111202505 陳山榆 碩士班 114222020 陳俊翰 | N7: 許慧君
A8: TRUE | B8: 其他 | D8: 46185 | E8: 國立中央大學-停水施工公告 | F8: 【緊急停水通知】 因發生緊急停水狀況，請全體師生節約用水。待水塔儲水耗盡後，館內將全面停水，敬請預先因應。 以下地點洗手台下方放置小型儲水桶備用： 1～7樓女生廁所 2樓、6樓、7樓男生廁所 如有需要，歡迎少量取用，切勿浪費。 感謝您的配合。 事由：科學二館與友好之櫻中間道路幹管破裂漏水緊急搶修。 各位師生： 因科學二館與友好之櫻中間道路幹管突發破裂，導致供水受到影響，目前已由相關單位緊急搶修中。為維護生活品質，工程人員正全力處理，請大家耐心等候。造成不便，敬請見諒。 施工中，不便之處敬祈見諒，施工中會停止供水，如遇有施工障礙或陣雨，可能延後供水。 受影響區域： 全校自來水、地下水停水(含中大新村)。 施工位置： 游泳池周邊自來水、地下水幹管。 施工日期及時間： 115年6月13日(星期六)。上午08：00至下午17:00。 施工廠商：京融水電工程有限公司 施工廠商電話：0932093643 營繕組電話：03-4227151#57307 謝先生 總務處 啟 | N8: 許慧君
A9: TRUE | B9: 招生 | D9: 46168 | E9: 『114學年國立中央大學物理學系五年取得學、碩士學位』獲推薦名單 | F9: 『114學年國立中央大學物理學系五年取得學、碩士學位』獲推薦名單(依學號排序)共12位： 111409506、112202006、112202010、112202012 112202013、112202017、112202028、112202501 112202503、112202516、112202517、112203016 注意事項：獲推薦之學生 1. 仍須報名下學年度本系碩士班甄試，報名時仍需依報名簡章規定，檢附包含指導教授在內至少兩封推薦書、專題研究報告(需符合註一之要求)與未來研究計畫等資料。 2. 如未能於大四取得學士學位即喪失資格。 註一：專題研究報告格式要求： (1) 報告不得少於6頁。 (2) 版面設定：A4紙，即長29.7公分，寬21公分。 (3) 格式：中文打字規格為每行繕打（行間不另留間距），英文打字規格為Single Space。 (4) 字體：以中英文撰寫均可。英文使用Times New Roman Font，中文使用標楷體，字體大小以12號為主。 理學院物理系五年取得學碩士學位推薦辦法1120926系務會議通過Download | G9: 理學院物理系五年取得學碩士學位推薦辦法1120926系務會議通過 | H9: https://www.phy.ncu.edu.tw/wp-content/uploads/2026/05/理學院物理系五年取得學碩士學位推薦辦法1120926系務會議通過.pdf | I9: Download | J9: https://www.phy.ncu.edu.tw/wp-content/uploads/2026/05/理學院物理系五年取得學碩士學位推薦辦法1120926系務會議通過.pdf | M9: https://www.phy.ncu.edu.tw/news/%e3%80%8e114%e5%ad%b8%e5%b9%b4%e5%9c%8b%e7%ab%8b%e4%b8%ad%e5%a4%ae%e5%a4%a7%e5%ad%b8%e7%89%a9%e7%90%86%e5%ad%b8%e7%b3%bb%e4%ba%94%e5%b9%b4%e5%8f%96%e5%be%97%e5%ad%b8%e3%80%81%e7%a2%a9%e5%a3%ab-3/ | N9: 許慧君
A10: TRUE | B10: 其他 | D10: 46167 | E10: S4-717暫停開放公告 | F10: 05/26(二)Open House 05/28(四)實驗物理課(陳俞融) 06/03(三)理學院EMI助教交流會 06/05(五)理學院英文演講比賽 06/12(五)理學院外籍生交流會 06/13(六)物理小年會 06/14(日)物理系迎新輔訓 非活動相關者請勿進入 學生自習請改至 721 讀書室 討論活動請多加利用各樓層電梯前討論區 及 627紀念書房 造成不便，敬請見諒，謝謝合作。 | M10: https://www.phy.ncu.edu.tw/news/s4-717%e6%9a%ab%e5%81%9c%e9%96%8b%e6%94%be%e5%85%ac%e5%91%8a-10/ | N10: 許慧君
A11: =TRUE() | B11: 其他 | D11: 46167 | E11: 115年05月23日-114學年度畢業照及畢業典禮 | F11: 更多相片陸續更新中 https://photos.app.goo.gl/62r9vPB1bRnMBghS7 | G11: https://photos.app.goo.gl/62r9vPB1bRnMBghS7 | H11: https://photos.app.goo.gl/62r9vPB1bRnMBghS7 | M11: https://www.phy.ncu.edu.tw/news/115%e5%b9%b405%e6%9c%8823%e6%97%a5-114%e5%ad%b8%e5%b9%b4%e5%ba%a6%e7%95%a2%e6%a5%ad%e7%85%a7%e5%8f%8a%e7%95%a2%e6%a5%ad%e5%85%b8%e7%a6%ae/ | N11: 許慧君
A12: =TRUE() | B12: 其他 | D12: 46167 | E12: 115學年度第1學期課程教學助教志願調查1150525 | F12: 中央大學物理系公告-115學年度第1學期課程教學助教志願調查 NCU Physics Departmental Notice-2026/2027 First Semester Teaching Assistant Application Form 物理系研究生欲申請擔任課程教學助教者，請於115年5月31日前填寫『課程教學助教志願表』(https://forms.gle/ZbTYtMT5guR3wpvVA)。 Physics Department graduate students who wish to serve as teaching assistants (TA), please fill in the TA Application Form before May 31, 2026 . (https://forms.gle/ZbTYtMT5guR3wpvVA)。 依研究生修業規定，修業期間碩士生至少需擔任一學期（上下學期皆可）課程助教、博士生至少需擔任兩學期（上下學期各一）課程助教，方可畢業。 The Graduate Student’s Course Regulations require master students to serve as TAs for at least one semester (once in either semester), while doctoral students must serve for at least two semesters (once in both semesters) as part of the criteria for graduation. 115-1助教TADownload 國立中央大學物理系研究生獎助學金辦法20210708系務會議通過Download | G12: https://forms.gle/ZbTYtMT5guR3wpvVA | H12: https://forms.gle/ZbTYtMT5guR3wpvVA | I12: https://forms.gle/ZbTYtMT5guR3wpvVA | J12: https://forms.gle/ZbTYtMT5guR3wpvVA | K12: 115-1助教TA | L12: https://www.phy.ncu.edu.tw/wp-content/uploads/2026/05/115-1助教TA.pdf | M12: https://www.phy.ncu.edu.tw/news/115%e5%ad%b8%e5%b9%b4%e5%ba%a6%e7%ac%ac1%e5%ad%b8%e6%9c%9f%e8%aa%b2%e7%a8%8b%e6%95%99%e5%ad%b8%e5%8a%a9%e6%95%99%e5%bf%97%e9%a1%98%e8%aa%bf%e6%9f%a51150525/ | N12: 許慧君
A13: =TRUE() | B13: 研討會 | D13: 46162 | E13: CHiP International Gravitational Wave Summer School 2026 | F13: Summer Chip poster A0 SIZE colorDownload | G13: Summer Chip poster A0 SIZE color | H13: https://www.phy.ncu.edu.tw/wp-content/uploads/2026/05/Summer-Chip-poster-A0-SIZE-color.pdf | I13: Download | J13: https://www.phy.ncu.edu.tw/wp-content/uploads/2026/05/Summer-Chip-poster-A0-SIZE-color.pdf | M13: https://www.phy.ncu.edu.tw/news/chip-international-gravitational-wave-summer-school-2026/ | N13: 許慧君
A14: =TRUE() | B14: 其他 | D14: 46162 | E14: 重力波實驗室誠徵博士後研究員1名 | F14: 【徵才單位】：國立中央大學物理系重力波實驗室。 【工作職缺】：博士後研究員1名。 【薪資待遇】：依據國家科學及技術委員會薪資標準(有相關經驗可提敘)。 【起聘時間】：2026/07/01~2026/07/31。 【徵求條件】：具國內、外物理相關系所之博士學位 【工作內容】：執行研究計畫，數據分析。 【工作地點】：國立中央大學統物理系（桃園市中壢區中大路300號 健雄館）。 【檢附資料】：履歷、自傳、博士論文及發表著作等相關資料 【應徵方式】： 1.應徵者請備妥電子資料，合併為一份 PDF 檔，檔名為「姓名_重力波實驗室博士後研究員」。資料審核通過者將通知面試時間,未通過者恕不通知。 2.將相關應徵文件於2026/06/15前e-mail至林助理：vivianbabylin@gmail.com | M14: https://www.phy.ncu.edu.tw/news/%e9%87%8d%e5%8a%9b%e6%b3%a2%e5%af%a6%e9%a9%97%e5%ae%a4%e8%aa%a0%e5%be%b5%e5%8d%9a%e5%a3%ab%e5%be%8c%e7%a0%94%e7%a9%b6%e5%93%a11%e5%90%8d/ | N14: 許慧君
A15: =TRUE() | B15: 演講 | D15: 46162 | E15: Colloquium_20260526_Uncovering the Physical Principles of Life with Artificial Cells - Symmetry Breaking and Energy Conversion of Active Cytoskeleton | F15: Colloquium_20260526Download | G15: Colloquium_20260526 | H15: https://www.phy.ncu.edu.tw/wp-content/uploads/2026/05/Colloquium_20260526.pdf | I15: Download | J15: https://www.phy.ncu.edu.tw/wp-content/uploads/2026/05/Colloquium_20260526.pdf | M15: https://www.phy.ncu.edu.tw/news/colloquium_20260526_uncovering-the-physical-principles-of-life-with-artificial-cells-symmetry-breaking-and-energy-conversion-of-active-cytoskeleton/ | N15: 許慧君
A16: =TRUE() | B16: 獎學金 | D16: 46162 | E16: 臺北市健鼎關懷教育基金會大學特定科系獎學金 | F16: 健鼎基金會大學特定科系申請辦法(1150518更新)Download 健鼎基金會大學特定科系申請辦法(1150518更新)Download | G16: 健鼎基金會大學特定科系申請辦法(1150518更新) | H16: https://www.phy.ncu.edu.tw/wp-content/uploads/2026/05/健鼎基金會大學特定科系申請辦法1150518更新.pdf | I16: Download | J16: https://www.phy.ncu.edu.tw/wp-content/uploads/2026/05/健鼎基金會大學特定科系申請辦法1150518更新.pdf | K16: 健鼎基金會大學特定科系申請辦法(1150518更新) | L16: https://www.phy.ncu.edu.tw/wp-content/uploads/2026/05/健鼎基金會大學特定科系申請辦法1150518更新.doc | M16: https://www.phy.ncu.edu.tw/news/%e8%87%ba%e5%8c%97%e5%b8%82%e5%81%a5%e9%bc%8e%e9%97%9c%e6%87%b7%e6%95%99%e8%82%b2%e5%9f%ba%e9%87%91%e6%9c%83%e5%a4%a7%e5%ad%b8%e7%89%b9%e5%ae%9a%e7%a7%91%e7%b3%bb%e7%8d%8e%e5%ad%b8%e9%87%91/ | N16: 許慧君
A17: =TRUE() | B17: 演講 | D17: 46162 | E17: 碩士生學位考試公告（唐萬昇） | F17: 姓名：唐萬昇 學號：112222015 口試日期：115/06/09 時間：14:30-17:00 借用地點：621 論文題目：Atomic-Scale Anisotropy Competition in Cr-Intercalated CrTe2 Ultrathin Films: DFT-SOT-LLG Simulation | M17: https://www.phy.ncu.edu.tw/news/%e7%a2%a9%e5%a3%ab%e7%94%9f%e5%ad%b8%e4%bd%8d%e8%80%83%e8%a9%a6%e5%85%ac%e5%91%8a%ef%bc%88%e5%94%90%e8%90%ac%e6%98%87%ef%bc%89/ | N17: 許慧君
A18: =TRUE() | B18: 演講 | D18: 46160 | E18: 5/27學術倫理講座 | M18: https://www.phy.ncu.edu.tw/news/5-27%e5%ad%b8%e8%a1%93%e5%80%ab%e7%90%86%e8%ac%9b%e5%ba%a7/ | N18: 許慧君
A19: =TRUE() | B19: 其他 | D19: 46160 | E19: S4-717暫停開放公告 | F19: 05/19(二)12-17高能活動 05/20(三)物理系個人申請 05/21(四)理學院學士班個人申請 05/23(六)理學院學士班畢業餐會 05/26(二)物理系高中生open house 06/03(三)理學院EMI助教交流會 06/12(五)理學院外籍生交流會 06/13(六)物理小年會 非活動相關者請勿進入 學生自習請改至 721 讀書室 討論活動請多加利用各樓層電梯前討論區 及 627紀念書房 造成不便，敬請見諒，謝謝合作。 | M19: https://www.phy.ncu.edu.tw/news/s4-717%e6%9a%ab%e5%81%9c%e9%96%8b%e6%94%be%e5%85%ac%e5%91%8a-9/ | N19: 許慧君
A20: =TRUE() | B20: 其他 | D20: 46160 | E20: 上傳論文不卡關--歡迎參加5月21日12:00-12:30「圖書館論文上傳繳交講習會」 | F20: 為了讓畢業生快速了解畢業論文各項上傳流程與注意事項， 圖書館將於民國115年5月21日(四)12:00-12:30開設一場線上講習會， 報名網址如下：https://cis.ncu.edu.tw/iNCU/messageNotice/activityManagement/activity/1782 亦提供中英文版的網頁與教學影片，歡迎參考： 1.中文版文字說明與教學影片： https://rapid.lib.ncu.edu.tw/libweek/guide/04-3.html 2.英文版文字說明與教學影片： https://rapid.lib.ncu.edu.tw/libweek/guide/en/04-3.html 國立中央大學圖書館 推廣服務組敬上 ncu57407@ncu.edu.tw (03)422-7151#57407 | G20: https://cis.ncu.edu.tw/iNCU/messageNotice/activityManagement | H20: https://cis.ncu.edu.tw/iNCU/messageNotice/activityManagement/activity/1782 | I20: https://rapid.lib.ncu.edu.tw/libweek/guide/04-3.html | J20: https://rapid.lib.ncu.edu.tw/libweek/guide/04-3.html | K20: https://rapid.lib.ncu.edu.tw/libweek/guide/en/04-3.html | L20: https://rapid.lib.ncu.edu.tw/libweek/guide/en/04-3.html | M20: https://www.phy.ncu.edu.tw/news/%e4%b8%8a%e5%82%b3%e8%ab%96%e6%96%87%e4%b8%8d%e5%8d%a1%e9%97%9c-%e6%ad%a1%e8%bf%8e%e5%8f%83%e5%8a%a05%e6%9c%8821%e6%97%a51200-1230%e3%80%8c%e5%9c%96%e6%9b%b8%e9%a4%a8%e8%ab%96%e6%96%87%e4%b8%8a/ | N20: 許慧君
A21: =TRUE() | B21: 其他 | D21: 46160 | E21: 強場物理與超快技術實驗室《誠徵雷射電漿工程師》 | F21: 本實驗室位於國立中央大學物理系，核心設施為100 TW超短脈衝雷射系統，並建有多座雷射電漿交互作用實驗站，研究方向涵蓋： 高階諧波的產生 雷射電漿電子與質子加速器 實驗室內天文學 強場雷射與超快光學診斷 我們致力於發展新世代高能量密度科學與先進加速器技術，並持續擴充實驗設施。現誠徵專任雷射電漿工程師，歡迎對超快雷射、光學系統與大型科研設施有熱情的夥伴加入團隊。 一、工作內容： 1. 高功率超短脈衝雷射系統之日常操作與維護。 2. 超快光學與雷射系統之優化與升級。 3. 協助雷射電漿交互作用實驗的進行。 4. 實驗室安全規範執行與環境管理。 二、資格： 物理、光電、電子/電機、機械工程等相關科系學士或碩士。具備光路架設、光學診斷經驗或對超快雷射系統有強烈興趣者尤佳。 三、薪資待遇：底薪依本校計畫專任人員報酬標準表，如已有年資可面議 學士級：36,300 元/月 碩士級：41,545 元/月 四、工作時間與福利： 工作時間：AM 9:00 – PM 6:00或 AM 8:00 – PM 5:00，含中午休息。 週休二日，國定假日比照政府行政機關。 若遇緊急維修或大型實驗需加班，提供完整補休機制。 依法辦理勞保、健保與退休／離職儲金 五、工作地點：國立中央大學物理系 310實驗室 (桃園中壢) --- 應徵方式： 請將個人履歷及相關資料，以電子郵件寄至 ckhuang@ncu.edu.tw 黃振崗老師收，信件主旨請註明：應徵雷射電漿工程師。 截止日期：2026年8月9日 實驗室網站： http://hfp.phy.ncu.edu.tw | M21: https://www.phy.ncu.edu.tw/news/%e5%bc%b7%e5%a0%b4%e7%89%a9%e7%90%86%e8%88%87%e8%b6%85%e5%bf%ab%e6%8a%80%e8%a1%93%e5%af%a6%e9%a9%97%e5%ae%a4%e3%80%8a%e8%aa%a0%e5%be%b5%e9%9b%b7%e5%b0%84%e9%9b%bb%e6%bc%bf%e5%b7%a5%e7%a8%8b%e5%b8%ab-2/ | N21: 許慧君
A22: =TRUE() | B22: 招生 | D22: 46156 | E22: 115學年度博士班考試錄取名單 | F22: https://admission.ncu.edu.tw/zh-TW/article/2026-05-14%2016:09:05/10 錄取通知書及成績單5/15以限時掛號郵寄到通訊地址 | G22: https://admission.ncu.edu.tw/zh-TW/article/2026-05-14%2016:0 | H22: https://admission.ncu.edu.tw/zh-TW/article/2026-05-14%2016:09:05/10 | M22: https://www.phy.ncu.edu.tw/news/115%e5%ad%b8%e5%b9%b4%e5%ba%a6%e5%8d%9a%e5%a3%ab%e7%8f%ad%e8%80%83%e8%a9%a6%e9%8c%84%e5%8f%96%e5%90%8d%e5%96%ae/ | N22: 許慧君
A23: =TRUE() | B23: 其他 | D23: 46156 | E23: 113、114學年度應修科目表修訂通過公告-跨領域課程規定 | F23: 113、114學年度應修科目表業已於115.03.11經114學年度第二學期第一次校課程委員會議修訂通過以下規定，在學1、2年級學生適用之： 備註二、2. 必須選修並通過外系課程6學分，不含通識中心、語言中心及體育室課程；課程名稱或課程內容與物理系課程相近者不予採認為跨領域課程。 各年級完整應修科目表請參閱 系網頁-系所簡介-系所規章-大學部相關規章 https://pdc.adm.ncu.edu.tw/static/file/19/1019/img/237/816533531.pdf https://pdc.adm.ncu.edu.tw/static/file/19/1019/img/310/252941592.pdf | G23: 系網頁-系所簡介-系所規章-大學部相關規章 | H23: https://www.phy.ncu.edu.tw/%e7%b3%bb%e6%89%80%e8%a6%8f%e7%ab%a0/ | I23: https://pdc.adm.ncu.edu.tw/static/file/19/1019/img/237/81653 | J23: https://pdc.adm.ncu.edu.tw/static/file/19/1019/img/237/816533531.pdf | K23: https://pdc.adm.ncu.edu.tw/static/file/19/1019/img/310/25294 | L23: https://pdc.adm.ncu.edu.tw/static/file/19/1019/img/310/252941592.pdf | M23: https://www.phy.ncu.edu.tw/news/113%e3%80%81114%e5%ad%b8%e5%b9%b4%e5%ba%a6%e6%87%89%e4%bf%ae%e7%a7%91%e7%9b%ae%e8%a1%a8%e4%bf%ae%e8%a8%82%e9%80%9a%e9%81%8e%e5%85%ac%e5%91%8a-%e8%b7%a8%e9%a0%98%e5%9f%9f%e8%aa%b2%e7%a8%8b%e8%a6%8f/ | N23: 吳菁穗
A24: =TRUE() | B24: 其他 | D24: 46156 | E24: 物理系 強場雷射實驗室 誠徵工讀助理 | F24: 人數需求： 1 名 薪資: 時薪 300 元（依規定投保勞健保）。 工讀時間: 每週 6 小時，可配合課表彈性排程。 工讀地點： 科學四館 3 樓 310 室 (100 TW強場雷射實驗室) 應徵條件： 本校在學學生（不限系所），對光學實驗環境、儀器維護有興趣者優先錄取。 需具備駕照與交通工具。 工作內容： 1. 實驗室環境維護、例行公安檢查。 2. 儀器與零件盤點與採購。 3. 實驗室硬體更新、修繕與行政支援。 應徵方式： 請將簡單個人履歷（包含姓名、系級、聯絡電話、一小段自我介紹或相關背景說明）寄至：白植豪教授 chpai@phy.ncu.edu.tw （郵件主旨請註明：應徵實驗室工讀生_系級_姓名） 聯絡電話： 03-422-7151 Ext. 65315 | M24: https://www.phy.ncu.edu.tw/news/%e7%89%a9%e7%90%86%e7%b3%bb-%e5%bc%b7%e5%a0%b4%e9%9b%b7%e5%b0%84%e5%af%a6%e9%a9%97%e5%ae%a4-%e8%aa%a0%e5%be%b5%e5%b7%a5%e8%ae%80%e5%8a%a9%e7%90%86/ | N24: 許慧君
A25: =TRUE() | B25: 其他 | D25: 46155 | E25: 114學年度大學部乙類學生畢業~「論文口試注意事項」 | F25: 請詳閱「乙類學生論文口試注意事項」。 各相關表單請用電腦繕打後印出（簽名除外）： 表單下載路徑：系網頁(http://www.phy.ncu.edu.tw/)→系所簡介→系所規章→大學部相關規章 本學期大學部領取畢業證書截止日為7/30(四)中午12點。 請於離校前將論文pdf檔email至以下信箱： cswu@ncu.edu.tw Email 標題請註明：繳交學士論文(學號+姓名)。 學士論文格式須比照“乙類學生論文格式條例”，未依格式或未繳交論文電子檔者不能畢業。 乙類學生論文口試注意事項11403Download | G25: http://www.phy.ncu.edu.tw/ | H25: https://l.facebook.com/l.php?u=https%3A%2F%2Fwww.phy.ncu.edu.tw%2F%3Ffbclid%3DIwZXh0bgNhZW0CMTAAYnJpZBExRk5UbndWeFpUZENVOHloQ3NydGMGYXBwX2lkEDIyMjAzOTE3ODgyMDA4OTIAAR41d1pWh3krVCkmBhiFYNtl1TzBSA7Iir7_e7W6dqQOId_ufCB71OyDprocZQ_aem_KfVB28ayPQa8JdDklCgk8g&h=AUB4e5yoEx1Iiv7IhQ66Jdz77AIZOS6k8uXHlP8NECLwTxovnj6RALs9ctjwFTGLSTxfrwSw7lkiyDk8HFXS3LYpkgdP7xDe-dK-sAkm9bm70b-Jsy8GszZMwqHCS8ebyPDBCuRZLBmi_FM1kYs9rUFuZEpyhp2h&__tn__=-UK-R&c[0]=AUCJPgu6rVrRn-jrf0YMBr118QeaJ8hhB7VsXIqP9Em3H-xIfYpr6B1CXg9nAiFf8xjkuRIN2R2SQ2YsHIA2p9XhxhA9wo3FceS_URw1m2QqESZJcfOruVTVKR_Y5ZWcot8IkxbWvMgSFbUQvljPPYcXPpOpfCKR-La4m9g-QQ | I25: 乙類學生論文口試注意事項11403 | J25: https://www.phy.ncu.edu.tw/wp-content/uploads/2026/05/乙類學生論文口試注意事項11403.pdf | K25: Download | L25: https://www.phy.ncu.edu.tw/wp-content/uploads/2026/05/乙類學生論文口試注意事項11403.pdf | M25: https://www.phy.ncu.edu.tw/news/114%e5%ad%b8%e5%b9%b4%e5%ba%a6%e5%a4%a7%e5%ad%b8%e9%83%a8%e4%b9%99%e9%a1%9e%e5%ad%b8%e7%94%9f%e7%95%a2%e6%a5%ad%e3%80%8c%e8%ab%96%e6%96%87%e5%8f%a3%e8%a9%a6%e6%b3%a8%e6%84%8f%e4%ba%8b%e9%a0%85/ | N25: 吳菁穗
A26: =TRUE() | B26: 演講 | D26: 46155 | E26: Colloquium_20260519_Superconductivity of topological states induced by proximity and Josephson coupling | F26: Colloquium_20260519Download | G26: Colloquium_20260519 | H26: https://www.phy.ncu.edu.tw/wp-content/uploads/2026/05/Colloquium_20260519.pdf | I26: Download | J26: https://www.phy.ncu.edu.tw/wp-content/uploads/2026/05/Colloquium_20260519.pdf | M26: https://www.phy.ncu.edu.tw/news/colloquium_20260519_superconductivity-of-topological-states-induced-by-proximity-and-josephson-coupling/ | N26: 許慧君
A27: =TRUE() | B27: 其他 | D27: 46154 | E27: 2026/05/23(六) 物理系撥穗典禮 | F27: 🎓 畢業餐會 11:50-13:10 (S4-625) 🎓 理學院合照 13:25-13:30 (S1-1F廣場) 🎓 撥穗典禮 13:50~16:00 (S4-209) 系主任致詞 撥穗儀式 謝師禮 🎓 師生合照 16:00-17:00 (S4-1F廣場) 🍰餐會備有豐盛美食，敬邀師長們與畢業生一同享用。 📸歡迎各位老師前來撥穗觀禮合影留念。 | M27: https://www.phy.ncu.edu.tw/news/2026-05-23%e5%85%ad-%e7%89%a9%e7%90%86%e7%b3%bb%e6%92%a5%e7%a9%97%e5%85%b8%e7%a6%ae/ | N27: 劉怡貞
A28: =TRUE() | B28: 招生 | C28: 高中生 | D28: 46154 | E28: 115學年度大學申請入學第二階段指定項目甄試【報到時間暨應試順序表】 | F28: 115學年度大學甄選申請入學第二階段指定項目甄試【報到時間表】如附件： 115學年度申請入學面試報到時間及應試順序表Download 甄試時間以115/05/20（三）當天實際進行的時間為主，請於指定報到時間內親自辦理報到。如預期會因故遲到者請務必事先告知，完成報到後將安排於最後一位考生之後遞補面試，不得異議。 注意事項： 請直接搭電梯到健雄館七樓717外辦理報到；報到時請攜帶「指定項目甄試通知函」及附照片之身分證件查驗。 為顧及全體考生之權益及公平性，甄試時間公告後不得要求更改。 當日家長汽車以車牌辨識入校，離校時請走人工車道(靠警衛室)並出示「指定項目甄試通知函」即可免繳停車費離校。 面試當天安排四場課程說明會(09:00、11:00、13:50、15:50)、實驗物理展覽室參觀及(下午)實驗課程觀摩，參觀時間於當天公布於報到處（視現場考生人數調整），歡迎考生及家長參加。 本系謹訂於115/05/26(二)舉辦OPEN HOUSE，誠摯邀請您參加，為統計參加人數及便當數量，請務必於5月24日(星期日)前完成報名表單提交。已填寫過表單者請勿重複提交。線上出席意願調查：https://forms.gle/UWgCtuhENMYRwSXE8 邀請函Download *本系謹訂於6/13 (六)辦理物理小年會，此為本系「實驗物理」以及「實驗專題」修課學生成 果發表之平台。高中生觀展報名時程為即日起至6月1日，意者請於報名期間進入物理小年會網站(https://ncuphyannualmeetin.wixsite.com/website-1) 點選 「觀展報名」。 | G28: 115學年度申請入學面試報到時間及應試順序表 | H28: https://www.phy.ncu.edu.tw/wp-content/uploads/2026/05/115學年度申請入學面試報到時間及應試順序表.pdf | I28: Download | J28: https://www.phy.ncu.edu.tw/wp-content/uploads/2026/05/115學年度申請入學面試報到時間及應試順序表.pdf | K28: 邀請函 | L28: https://www.phy.ncu.edu.tw/wp-content/uploads/2026/05/邀請函.pdf | M28: https://www.phy.ncu.edu.tw/news/115%e5%ad%b8%e5%b9%b4%e5%ba%a6%e5%a4%a7%e5%ad%b8%e7%94%b3%e8%ab%8b%e5%85%a5%e5%ad%b8%e7%ac%ac%e4%ba%8c%e9%9a%8e%e6%ae%b5%e6%8c%87%e5%ae%9a%e9%a0%85%e7%9b%ae%e7%94%84%e8%a9%a6%e3%80%90%e5%a0%b1/ | N28: 吳菁穗
A29: =TRUE() | B29: 研討會 | D29: 46153 | E29: 2026物理小年會 | F29: 時間： 2026/06/13(六) 08:00 – 17:30 地點：國立中央大學物理學系科學四館（健雄館） 學生報名時程： 4/15 – 6/1 繳交海報時程： 5/11 - 6/6 詳細議程請見本會網站： https://ncuphyannualmeetin.wixsite.com/website-1 | G29: https://ncuphyannualmeetin.wixsite.com/website-1 | H29: https://ncuphyannualmeetin.wixsite.com/website-1 | M29: https://www.phy.ncu.edu.tw/news/2026%e7%89%a9%e7%90%86%e5%b0%8f%e5%b9%b4%e6%9c%83/ | N29: 許慧君
A30: =TRUE() | B30: 招生 | D30: 46153 | E30: 『114學年國立中央大學物理學系五年取得學、碩士學位』口試通知 | F30: 請申請同學至物理系辦公室(S4-629)領取口試通知單。 口試序號標示於個人口試通知單上。 114學年度五年學碩口試通知Download | G30: 114學年度五年學碩口試通知 | H30: https://www.phy.ncu.edu.tw/wp-content/uploads/2026/05/114學年度五年學碩口試通知.pdf | I30: Download | J30: https://www.phy.ncu.edu.tw/wp-content/uploads/2026/05/114學年度五年學碩口試通知.pdf | M30: https://www.phy.ncu.edu.tw/news/%e3%80%8e114%e5%ad%b8%e5%b9%b4%e5%9c%8b%e7%ab%8b%e4%b8%ad%e5%a4%ae%e5%a4%a7%e5%ad%b8%e7%89%a9%e7%90%86%e5%ad%b8%e7%b3%bb%e4%ba%94%e5%b9%b4%e5%8f%96%e5%be%97%e5%ad%b8%e3%80%81%e7%a2%a9%e5%a3%ab-2/ | N30: 許慧君
A31: =TRUE() | B31: 其他 | D31: 46153 | E31: 物理系教室異動公告1150520-0521 | F31: 因應5/20(三)物理系個人申請招生、5/21(四)理學院學士班個人申請招生，教室異動，造成不便請見諒。 原教室日期時間課程新教室 S4-6235/20(三)13-18PH2030B-實驗物理與方法II(郭家銘)S4-202 S4-6255/20(三)09-12PH6070*-非線性動力學(黎璧賢)S4-204 S4-6255/20(三)14-17PH6012*-統計力學 Ｉ(陳炯豪)S4-204 S4-6215/21(四)10-13PH7029*-高能物理I(江祖永)S4-208理論中心教室 | M31: https://www.phy.ncu.edu.tw/news/%e7%89%a9%e7%90%86%e7%b3%bb%e6%95%99%e5%ae%a4%e7%95%b0%e5%8b%95%e5%85%ac%e5%91%8a1150520-0521/ | N31: 許慧君
A32: =TRUE() | B32: 其他 | D32: 46150 | E32: 2026 台積電博士獎學金(第二梯次)即日起開放申請，2026年05月30日截止收件。 | F32: 獎助內容： 博士修業期間每年獎助新台幣50萬元整，至多獎助五年 由台積資深主管擔任業師，協助了解產業、技術發展階段與挑戰 在學期間提供台積實習機會 歡迎符合以下申請資格的同學們提出申請： 預計於2026年攻讀國內大學半導體相關科系博士學位(含申請中)之學、碩士班，或是已入學之博士一年級，並經指導教授推薦者 不限制已(欲)申請國家級或非營利機構獎學金者 具中華民國國籍 詳細資訊請參見台積官方連結：https://careers.tsmc.com/zh_TW/CampusPhD | G32: https://careers.tsmc.com/zh_TW/CampusPhD | H32: https://careers.tsmc.com/zh_TW/CampusPhD | M32: https://www.phy.ncu.edu.tw/news/2026-%e5%8f%b0%e7%a9%8d%e9%9b%bb%e5%8d%9a%e5%a3%ab%e7%8d%8e%e5%ad%b8%e9%87%91%e7%ac%ac%e4%ba%8c%e6%a2%af%e6%ac%a1%e5%8d%b3%e6%97%a5%e8%b5%b7%e9%96%8b%e6%94%be%e7%94%b3%e8%ab%8b%ef%bc%8c2026%e5%b9%b4/ | N32: 劉怡貞
A33: =TRUE() | B33: 獎學金 | D33: 46148 | E33: CTCI Foundation Overseas Student Employment in Taiwan Grant Application Information | F33: 本獎助金申請相關資訊如下： 中文說明：https://www.ctci.org.tw/8838/talent/46808/46809/46811/ English Information：https://www.ctci.org.tw/8831/8838/talent_en/46819/ 申請相關文件（中文版）（皆可於上述網站下載）： • 2026年境外生留臺就業獎助金申請須知（中文版） • 2026年境外生留臺就業獎助金申請須知（英文版） • 2026年境外留臺就業獎助金－開放申請校系（所）一覽表 • 2026年境外生留臺就業獎助金申請書－系（所）推薦 • 2026年境外生留臺就業獎助金申請書－曾獲中技社「境外生研究獎學金」 Application Documents (English Version) • Application Information for 2026 CTCI Foundation Overseas Student Employment in Taiwan Grant • Designated Departments/Institutes and Universities for 2026 CTCI Foundation Overseas Student Employment in Taiwan Grant • Application Form – Department or Institute-Nominated Applicant • Application Form – Former Recipients of the CTCI Foundation Research Scholarship for Overseas Graduate Students 申請及送件說明：有意申請者請備妥申請文件電子檔及紙本文件，於2026年8月24日（一）中午12:00前送至物理系辦公室。 Application and submission instructions: Interested applicants should prepare both electronic and hard copies of their application documents and submit them to the Department of Physics office before 12:00 noon on Monday, August 24, 2026. | G33: https://www.ctci.org.tw/8838/talent/46808/46809/46811/ | H33: https://www.ctci.org.tw/8838/talent/46808/46809/46811/ | I33: https://www.ctci.org.tw/8831/8838/talent_en/46819/ | J33: https://www.ctci.org.tw/8831/8838/talent_en/46819/ | M33: https://www.phy.ncu.edu.tw/news/ctci-foundation-overseas-student-employment-in-taiwan-grant-application-information/ | N33: 許慧君
A34: =TRUE() | B34: 獎學金 | D34: 46148 | E34: 中技社「2026年境外生留臺就業獎助金」 | F34: 本獎助金申請相關資訊如下： 中文說明：https://www.ctci.org.tw/8838/talent/46808/46809/46811/ English Information：https://www.ctci.org.tw/8831/8838/talent_en/46819/ 申請相關文件（中文版）（皆可於上述網站下載）： • 2026年境外生留臺就業獎助金申請須知（中文版） • 2026年境外生留臺就業獎助金申請須知（英文版） • 2026年境外留臺就業獎助金－開放申請校系（所）一覽表 • 2026年境外生留臺就業獎助金申請書－系（所）推薦 • 2026年境外生留臺就業獎助金申請書－曾獲中技社「境外生研究獎學金」 Application Documents (English Version) • Application Information for 2026 CTCI Foundation Overseas Student Employment in Taiwan Grant • Designated Departments/Institutes and Universities for 2026 CTCI Foundation Overseas Student Employment in Taiwan Grant • Application Form – Department or Institute-Nominated Applicant • Application Form – Former Recipients of the CTCI Foundation Research Scholarship for Overseas Graduate Students 申請及送件說明：有意申請者請備妥申請文件電子檔及紙本文件，於2026年8月24日（一）中午12:00前送至物理系辦公室。 Application and submission instructions: Interested applicants should prepare both electronic and hard copies of their application documents and submit them to the Department of Physics office before 12:00 noon on Monday, August 24, 2026. | G34: https://www.ctci.org.tw/8838/talent/46808/46809/46811/ | H34: https://www.ctci.org.tw/8838/talent/46808/46809/46811/ | I34: https://www.ctci.org.tw/8831/8838/talent_en/46819/ | J34: https://www.ctci.org.tw/8831/8838/talent_en/46819/ | M34: https://www.phy.ncu.edu.tw/news/%e4%b8%ad%e6%8a%80%e7%a4%be%e3%80%8c2026%e5%b9%b4%e5%a2%83%e5%a4%96%e7%94%9f%e7%95%99%e8%87%ba%e5%b0%b1%e6%a5%ad%e7%8d%8e%e5%8a%a9%e9%87%91%e3%80%8d/ | N34: 許慧君
A35: =TRUE() | B35: 演講 | D35: 46148 | E35: Colloquium_20260512_Harnessing Metastable States for Next-Generation Quantum Sensors and Clocks | F35: Colloquium_20260512Download | G35: Colloquium_20260512 | H35: https://www.phy.ncu.edu.tw/wp-content/uploads/2026/05/Colloquium_20260512-1.pdf | I35: Download | J35: https://www.phy.ncu.edu.tw/wp-content/uploads/2026/05/Colloquium_20260512-1.pdf | M35: https://www.phy.ncu.edu.tw/news/colloquium_20260512_harnessing-metastable-states-for-next-generation-quantum-sensors-and-clocks/ | N35: 許慧君
A36: =TRUE() | B36: 演講 | D36: 46147 | E36: 博士生學位考試公告(施承瑋) | F36: 姓名：施承瑋 學號 ：111282001 口試日期及時間 5/29 10:30 am 借用口試地點: 625 論文題目: Measurement of charged hadron multiplicity in Au+Au collisions at √sNN = 200 GeV with the sPHENIX detector | M36: https://www.phy.ncu.edu.tw/news/%e5%8d%9a%e5%a3%ab%e7%94%9f%e5%ad%b8%e4%bd%8d%e8%80%83%e8%a9%a6%e5%85%ac%e5%91%8a%e6%96%bd%e6%89%bf%e7%91%8b/ | N36: 許慧君
A37: =TRUE() | B37: 獎學金 | D37: 46146 | E37: 國立中央大學補助學生受美國對等關稅影響致生活變故試辦計畫 | F37: 國立中央大學補助學生受美國對等關稅影響致生活變故試辦計畫Download 申請須知懶人包.Download | G37: 國立中央大學補助學生受美國對等關稅影響致生活變故試辦計畫 | H37: https://www.phy.ncu.edu.tw/wp-content/uploads/2026/05/國立中央大學補助學生受美國對等關稅影響致生活變故試辦計畫.pdf | I37: Download | J37: https://www.phy.ncu.edu.tw/wp-content/uploads/2026/05/國立中央大學補助學生受美國對等關稅影響致生活變故試辦計畫.pdf | K37: 申請須知懶人包. | L37: https://www.phy.ncu.edu.tw/wp-content/uploads/2026/05/申請須知懶人包.pdf | M37: https://www.phy.ncu.edu.tw/news/%e5%9c%8b%e7%ab%8b%e4%b8%ad%e5%a4%ae%e5%a4%a7%e5%ad%b8%e8%a3%9c%e5%8a%a9%e5%ad%b8%e7%94%9f%e5%8f%97%e7%be%8e%e5%9c%8b%e5%b0%8d%e7%ad%89%e9%97%9c%e7%a8%85%e5%bd%b1%e9%9f%bf%e8%87%b4%e7%94%9f%e6%b4%bb/ | N37: 許慧君
A38: =TRUE() | B38: 其他 | D38: 46146 | E38: 失物招領(115.05.04) | F38: 有遺失下列物品者，請於115.05.30前至物理系辦(S4-629)認領! | M38: https://www.phy.ncu.edu.tw/news/%e5%a4%b1%e7%89%a9%e6%8b%9b%e9%a0%98115-05-04/ | N38: 許慧君
A39: =TRUE() | B39: 獎學金 | D39: 46146 | E39: 聯電劉炯朗博士生獎學金 | F39: 有鑑於台灣半導體需要更多優秀博士人才投注前端研究，聯華電子科技文教基金會為紀念劉炯朗院士一生致力於科技人才培育的理念， 以及為產業培養人才，設置「聯電劉炯朗博士生獎學金」，鼓勵國內優秀博士班學生專心致力於學術研究與技術創新，以提升國內整體 半導體產業實力。 https://www.umc.com/zh-TW/Html/scholarships 獎學金申請網頁 連結 https://www.surveycake.com/s/q4e9P 獎學金申請文件 連結 https://reurl.cc/3OmNGR | G39: https://www.umc.com/zh-TW/Html/scholarships | H39: https://www.umc.com/zh-TW/Html/scholarships | I39: https://www.surveycake.com/s/q4e9P | J39: https://www.surveycake.com/s/q4e9P | K39: https://reurl.cc/3OmNGR | L39: https://reurl.cc/3OmNGR | M39: https://www.phy.ncu.edu.tw/news/%e8%81%af%e9%9b%bb%e5%8a%89%e7%82%af%e6%9c%97%e5%8d%9a%e5%a3%ab%e7%94%9f%e7%8d%8e%e5%ad%b8%e9%87%91-2/ | N39: 許慧君
A40: =TRUE() | B40: 獎學金 | D40: 46142 | E40: 教育部114學年度「大專校院學生雙語化學習計畫」出國補助申請 | F40: 申請期間 : 115年05月04日至05月18日 補助期間(出國期間) : 114年8月1日-115年12月31日(已回國者仍可申請，惟須符合補助規定) 補助範圍 : [本國籍]學生，含大學部、碩士及博士班學生 補助規定 : 同一出國事由如獲本計畫審核通過 [可以] 與自籌收入(如捐款/結餘款)分攤補助 [不可以] 與其他政府經費(如國科會計畫/國科會專案補助/教育部計畫)分攤補助 補助項目 : 學生赴國外進修、 交流及出席國際會議所需之相關費用，包含註冊費(學費)、學分費、來回機票費、國外生活費。 交流機構與區域 : 交流機構與區域： 學生提出申請時，預定研習或交換之海外學校(或研究機構)須符合QS世界大學排名、泰晤士高等教育世界大學排名、美國新聞與世界報導世界大學排名前1,000名，或國家科學及技術委員會公告之國外研習機構，惟補助範圍不包含陸、 港、澳地區。 有意申請者請填寫下列表單 https://forms.gle/ccLFoCqcnBGfvNow6 | G40: https://forms.gle/ccLFoCqcnBGfvNow6 | H40: https://forms.gle/ccLFoCqcnBGfvNow6 | M40: https://www.phy.ncu.edu.tw/news/%e6%95%99%e8%82%b2%e9%83%a8114%e5%ad%b8%e5%b9%b4%e5%ba%a6%e3%80%8c%e5%a4%a7%e5%b0%88%e6%a0%a1%e9%99%a2%e5%ad%b8%e7%94%9f%e9%9b%99%e8%aa%9e%e5%8c%96%e5%ad%b8%e7%bf%92%e8%a8%88%e7%95%ab%e3%80%8d-3/ | N40: 許慧君
A41: =TRUE() | B41: 其他 | D41: 46141 | E41: 2026第22屆吳大猷科學營(單位推薦 系上受理截止日2026.05.15) | F41: 科學營招收學員採「學系推薦」及「自由報名」兩種方式，由於名額有限，錄取名額以學系推薦優先，自由報名次之。 時間：115年8月2~7日 地點：新竹北埔麻布山林 主題：綠能的未來：機會與挑戰(The Future of Green Energy-Opportunities and Challenges) 參加對象：臺灣各大學物理、電機、光電工程、能源、核子工程、材料、化工、化學、科技法律等相關學系大學部及研究所學生得申請報名，預計招收八十名。中港澳、新加坡、馬來西亞學員另外遴選。 報名方式及費用： 一、「學系推薦」五位名額：請檢附以下資料，系上受理截止日2026.05.15(五)。 推薦學員報名表(附檔)。 繳交一篇800-1,000字的短文，內容含自傳、個人對相關課題的興趣、曾經參加過的相關活動等。 教師推薦表格(下載)。 今年為升研一者(應屆畢業生)，請附上已經考上研究所之相關證明文件。 二、「自由報名」參閱：活動連結，報名至5月22日(星期五)截止。 三、營隊參加費用：三千元。 推薦學員報名表2026Download 吳大猷學術基金會函文202604Download | G41: 下載 | H41: https://www.phys.sinica.edu.tw/~tywufund/camp/2026/download/recommendation.doc | I41: 活動連結 | J41: https://www.phys.sinica.edu.tw/~tywufund/camp/2026/index.php | K41: 推薦學員報名表2026 | L41: https://www.phy.ncu.edu.tw/wp-content/uploads/2026/04/推薦學員報名表2026-2.pdf | M41: https://www.phy.ncu.edu.tw/news/2026%e7%ac%ac22%e5%b1%86%e5%90%b3%e5%a4%a7%e7%8c%b7%e7%a7%91%e5%ad%b8%e7%87%9f%e5%96%ae%e4%bd%8d%e6%8e%a8%e8%96%a6-%e7%b3%bb%e4%b8%8a%e5%8f%97%e7%90%86%e6%88%aa%e6%ad%a2%e6%97%a52026-05-15/ | N41: 劉怡貞
A42: =TRUE() | B42: 演講 | D42: 46140 | E42: Colloquium_20260505_Revisiting Magnetic Heterostructures - From Deterministic to Stochastic Spintronics Devices | F42: Colloquium_20260505Download | G42: Colloquium_20260505 | H42: https://www.phy.ncu.edu.tw/wp-content/uploads/2026/04/Colloquium_20260505.pdf | I42: Download | J42: https://www.phy.ncu.edu.tw/wp-content/uploads/2026/04/Colloquium_20260505.pdf | M42: https://www.phy.ncu.edu.tw/news/colloquium_20260505_revisiting-magnetic-heterostructures-from-deterministic-to-stochastic-spintronics-devices/ | N42: 許慧君
A43: =TRUE() | B43: 其他 | D43: 46140 | E43: S4-717暫停開放公告 | F43: 04/30(四)11-16理學院宣傳影片拍攝 05/18(一)09-14理學院第三屆學生英文演說比賽 05/20(三)物理系個人申請 05/21(四)理學院學士班個人申請 06/03(三)理學院EMI助教交流會 06/12(五)理學院外籍生交流會 06/13(六)物理小年會 非活動相關者請勿進入 學生自習請改至 721 讀書室 討論活動請多加利用各樓層電梯前討論區 及 627紀念書房 造成不便，敬請見諒，謝謝合作。 | M43: https://www.phy.ncu.edu.tw/news/s4-717%e6%9a%ab%e5%81%9c%e9%96%8b%e6%94%be%e5%85%ac%e5%91%8a-7/ | N43: 許慧君
A44: =TRUE() | B44: 招生 | D44: 46139 | E44: 115學年度博士班考試入學可參加複試名單 | F44: 口試通知紙本及初試成績單於4/28以掛號郵寄至通訊地址 115博班考試入學口試通知（物理）Download | G44: 115博班考試入學口試通知（物理） | H44: https://www.phy.ncu.edu.tw/wp-content/uploads/2026/04/115博班考試入學口試通知（物理）.pdf | I44: Download | J44: https://www.phy.ncu.edu.tw/wp-content/uploads/2026/04/115博班考試入學口試通知（物理）.pdf | M44: https://www.phy.ncu.edu.tw/news/115%e5%ad%b8%e5%b9%b4%e5%ba%a6%e5%8d%9a%e5%a3%ab%e7%8f%ad%e8%80%83%e8%a9%a6%e5%85%a5%e5%ad%b8%e5%8f%af%e5%8f%83%e5%8a%a0%e8%a4%87%e8%a9%a6%e5%90%8d%e5%96%ae/ | N44: 許慧君
A45: =TRUE() | B45: 其他 | D45: 46139 | E45: 2026光世代實驗技術預備學校 | F45: 2026光世代實驗技術預備學校海報定稿20260424-1-已壓縮Download | G45: 2026光世代實驗技術預備學校海報定稿20260424-1-已壓縮 | H45: https://www.phy.ncu.edu.tw/wp-content/uploads/2026/04/2026光世代實驗技術預備學校海報定稿20260424-1-已壓縮.pdf | I45: Download | J45: https://www.phy.ncu.edu.tw/wp-content/uploads/2026/04/2026光世代實驗技術預備學校海報定稿20260424-1-已壓縮.pdf | M45: https://www.phy.ncu.edu.tw/news/2026%e5%85%89%e4%b8%96%e4%bb%a3%e5%af%a6%e9%a9%97%e6%8a%80%e8%a1%93%e9%a0%90%e5%82%99%e5%ad%b8%e6%a0%a1/ | N45: 許慧君
A46: =TRUE() | B46: 其他 | D46: 46139 | E46: 115年5月2日全大運開幕，校園交通管制內容。 | F46: 本校將於 115 年 5 月 2 日（星期六）舉辦115 年全大運開幕典禮，為確保活動順利及校園交通順暢，當日將實施以下交通管制措施，並附「校園可行駛路線及停車區域示意圖」供參考，煩請大家配合，造成不便，敬請見諒。非常感謝！ 【管制時間】115 年 5 月 2 日 00:00 - 20:30 【行車方式】 入校建議：當日請儘可能由學校前門進入。 行車方向：入校後一律往右轉單向行駛。 【公車路線】 不繞駛校園。 車輛入校後，一律停靠本校「行政大樓」前(臨時站)提供乘客上下車。 車輛完成乘客上下車後，即駛離校園。 【封閉部份路段】溜冰場至排球場面對教研大樓之前方道路淨空，禁止通行。 【管制部份停車區】除以下停車區暫不開放停車外，其他停車區、校園道路黃線區皆可停車，或依現場交管人員指引停放。 游泳池至北村出入口停車區 工程五館停車場出入口之左側停車區(新村三區旁) 排球場至白色能源屋之路邊停車區 教研大樓地下停車場 總務處 敬啟 全大運開幕_校園可行駛路線及停車區域示意圖_v20260425Download | G46: 全大運開幕_校園可行駛路線及停車區域示意圖_v20260425 | H46: https://www.phy.ncu.edu.tw/wp-content/uploads/2026/04/全大運開幕_校園可行駛路線及停車區域示意圖_v20260425.pdf | I46: Download | J46: https://www.phy.ncu.edu.tw/wp-content/uploads/2026/04/全大運開幕_校園可行駛路線及停車區域示意圖_v20260425.pdf | M46: https://www.phy.ncu.edu.tw/news/115%e5%b9%b45%e6%9c%882%e6%97%a5%e5%85%a8%e5%a4%a7%e9%81%8b%e9%96%8b%e5%b9%95%ef%bc%8c%e6%a0%a1%e5%9c%92%e4%ba%a4%e9%80%9a%e7%ae%a1%e5%88%b6%e5%85%a7%e5%ae%b9%e3%80%82/ | N46: 許慧君
A47: =TRUE() | B47: 研討會 | D47: 46135 | E47: 2026 強場雷射與核融合暑期研習 | F47: 2026 強場實驗室暑假實習海報 (003)Download | G47: 2026 強場實驗室暑假實習海報 (003) | H47: https://www.phy.ncu.edu.tw/wp-content/uploads/2026/04/2026-強場實驗室暑假實習海報-003.pdf | I47: Download | J47: https://www.phy.ncu.edu.tw/wp-content/uploads/2026/04/2026-強場實驗室暑假實習海報-003.pdf | M47: https://www.phy.ncu.edu.tw/news/2026-%e5%bc%b7%e5%a0%b4%e9%9b%b7%e5%b0%84%e8%88%87%e6%a0%b8%e8%9e%8d%e5%90%88%e6%9a%91%e6%9c%9f%e7%a0%94%e7%bf%92/ | N47: 許慧君
A48: =TRUE() | B48: 演講 | D48: 46133 | E48: Complex System and Biophysics Seminar 20260423 | F48: Complex System and Biophysics Seminar_20260423Download | G48: Complex System and Biophysics Seminar_20260423 | H48: https://www.phy.ncu.edu.tw/wp-content/uploads/2026/04/Complex-System-and-Biophysics-Seminar_20260423.pdf | I48: Download | J48: https://www.phy.ncu.edu.tw/wp-content/uploads/2026/04/Complex-System-and-Biophysics-Seminar_20260423.pdf | M48: https://www.phy.ncu.edu.tw/news/complex-system-and-biophysics-seminar-20260423/ | N48: 許慧君
A49: =TRUE() | B49: 演講 | D49: 46133 | E49: Colloquium_20260428_From Eikonal to Entanglement | F49: Colloquium_20260428Download | G49: Colloquium_20260428 | H49: https://www.phy.ncu.edu.tw/wp-content/uploads/2026/04/Colloquium_20260428.pdf | I49: Download | J49: https://www.phy.ncu.edu.tw/wp-content/uploads/2026/04/Colloquium_20260428.pdf | M49: https://www.phy.ncu.edu.tw/news/colloquium_20260428_from-eikonal-to-entanglement/ | N49: 許慧君
A50: =TRUE() | B50: 其他 | D50: 46132 | E50: 1150422教室異動公告 | F50: 因應4/22(三)系評鑑 S4-625教室異動 造成不便請見諒 課號時間原教室新教室 PH6070*-非線性動力學 (黎璧賢)09-12S4-625S4-623研討室 PH6012*-統計力學 Ｉ (陳炯豪)14-17S4-625S4-204教室 | M50: https://www.phy.ncu.edu.tw/news/1150422%e6%95%99%e5%ae%a4%e7%95%b0%e5%8b%95%e5%85%ac%e5%91%8a/ | N50: 許慧君
A51: =TRUE() | B51: 其他 | D51: 46132 | E51: S4-717暫停開放公告 | F51: 04/24(五)10-12理學院EMI教師交流會 04/30(四)11-16國際處宣傳影片拍攝 05/18(一)09-14理學院第三屆學生英文演說比賽 05/20(三)物理系個人申請 05/21(四)理學院學士班個人申請 05/26(二)物理系高中生open house 06/03(三)理學院EMI助教交流會 06/12(五)理學院外籍生交流會 06/13(六)物理小年會 非活動相關者請勿進入 學生自習請改至 721 讀書室 討論活動請多加利用各樓層電梯前討論區 及 627紀念書房 造成不便，敬請見諒，謝謝合作。 | M51: https://www.phy.ncu.edu.tw/news/s4-717%e6%9a%ab%e5%81%9c%e9%96%8b%e6%94%be%e5%85%ac%e5%91%8a-8/ | N51: 許慧君
A52: =TRUE() | B52: 其他 | D52: 46127 | E52: NCU Commencement 2026 Announcement | F52: https://club.adm.ncu.edu.tw/graduate | G52: https://club.adm.ncu.edu.tw/graduate | H52: https://club.adm.ncu.edu.tw/graduate | M52: https://www.phy.ncu.edu.tw/news/ncu-commencement-2026-announcement/ | N52: 許慧君
A53: =TRUE() | B53: 其他 | D53: 46127 | E53: 114 學年度畢業典禮 | F53: https://club.adm.ncu.edu.tw/graduate | G53: https://club.adm.ncu.edu.tw/graduate | H53: https://club.adm.ncu.edu.tw/graduate | M53: https://www.phy.ncu.edu.tw/news/114-%e5%ad%b8%e5%b9%b4%e5%ba%a6%e7%95%a2%e6%a5%ad%e5%85%b8%e7%a6%ae/ | N53: 許慧君
A54: =TRUE() | B54: 演講 | D54: 46126 | E54: Colloquium_20260421_Numerical studies of the morphodynamics of dynamic cell assemblies | F54: Colloquium_20260421Download | G54: Colloquium_20260421 | H54: https://www.phy.ncu.edu.tw/wp-content/uploads/2026/04/Colloquium_20260421.pdf | I54: Download | J54: https://www.phy.ncu.edu.tw/wp-content/uploads/2026/04/Colloquium_20260421.pdf | M54: https://www.phy.ncu.edu.tw/news/colloquium_20260421_numerical-studies-of-the-morphodynamics-of-dynamic-cell-assemblies/ | N54: 許慧君
A55: =TRUE() | B55: 其他 | D55: 46126 | E55: 【全校公共區域環境消毒公告】 | F55: 國立中央大學全校環境公共區域消毒公告 National Central University Environmental anti - mosquito measures Notice 時 間：115年4月27日上午8：00～17：30 Anti- mosquito measures time: April 27th , 2026 8:00 a.m. to 17:30 p.m. 消毒原由及範圍 (Reasons and range of anti- mosquito measures)： 由於天候漸漸高溫炎熱，恐使大量病媒蚊孳生，擬針對全校戶外公共區域陽光照射不到之陰暗角落、水溝（含各館舍屋基周邊）及緊鄰本校西北側外圍之排水溝渠，進行消毒防治工作，施工期間有藥劑警示味道，請各館舍暫時將窗戶關閉，造成不便，敬請見諒。 請各館舍確實執行「巡、倒、清、刷」，如有積水情形應立即清除，並配合於施作3天前完成屋基周圍水溝落葉及污泥清理，以阻絕病媒蚊孳生及登革熱，並達環境消毒之效果。 The gradually increasing high temperature may cause a large number of vector mosquitoes to breed. It is planned to anti- mosquito measures for the dark corners and the gutterways of the outdoor public areas, including the periphery of all the buildings, and the drainages adjacent to the western side of the campus. During the construction period, There may produce unpleasant smells. Please all the buildings close windows temporarily. Apologize for the inconvenience.Please ensure that each building carries out "patrol, overturn, clean, and scrub" measures diligently. Each facility is requested to diligently carry out ‘inspection, draining, cleaning, and scrubbing.’ Any stagnant water should be removed immediately, and in coordination, the cleaning of leaves and sludge from the ditches around building foundations should be completed at least three days prior to implementation, in order to prevent the breeding of disease-carrying mosquitoes and dengue fever, as well as to achieve the effect of environmental disinfection. 預計消毒範圍：建物館舍外屋基周邊水溝及戶外公共區域。施作順序如附件 Expected range of anti- mosquito measures : the periphery and the gutterways of the following buildings, and the outdoor public areas. [註]若本次施作時逢下雨或強風等其他不適合噴灑因素時，將於115年5月1日施作，不再另行公告，謝謝合作!! If there is any unsuitable situation for spraying pesticide,such as raining or strong wind, the anti- mosquito measures will be expected to conducted on May 1th without any futher notice. Thank you for your cooperation! 施作廠商：信實公寓大廈管理維護股份有限公司 電話：(03)393-7960 (病媒防治許可執照字號：竹縣環藥病媒字第04-019號) 廠商現場專業技術人員：王書文 電話：0925-089359 本案承辦人：事務組吳小姐 電話：(03)422-7151分機57316 防治對象：蟑螂、跳蚤、蚊子、孑孓及蛾蚋 防治方式：使用動力噴霧機，針對全校建築物戶外屋基周圍、水溝及周邊樹(灌)木、樹葉背面蚊蟲易棲習處，實施殘效噴灑。 戶外公共區域及屋基陰暗處、排水溝 Outdoor public areas and periphery of the buildings,and the gutterways. 注意事項(Attention): 1. 請全校教職員生、寵物在消毒時間內儘量減少在校園戶外活動，以避免吸入消毒藥劑，並請準備口罩於必要時配戴。 In order to prevent from inhaling disinfectant, please avoid doing outdoor activity in the campus during the sterilization. Besides, please prepare the mask to wear if it is necessary. 2. 本類藥劑正常使用時很少引起中毒，但可能對皮膚略有刺激反應，若大量過度接觸或誤食時，可能引起過度敏感、活動減少、俯臥、疲軟、流涎、咳嗽、流鼻水等症狀。 This disinfectant rarely cause poisoning during normal use. However, it may lead to skin irritate. When you touch too much disinfectant or eat by mistake, it may cause allergy, languor, drooling, coughing, and running nose, etc. 3. 解毒及急救方式：眼睛或皮膚不慎接觸藥液時，應以大量清水連續沖洗15分鐘後再送醫診治。若不慎吸入藥霧，應立即將病患移至通風處再送醫診治。如有緊急狀況，可致電(02)2875-7525 #821臺北榮民總醫院臨床毒物與職業醫學科尋解，必要時持本藥劑標…（內容過長截斷，完整內容見原始連結） | M55: https://www.phy.ncu.edu.tw/news/%e3%80%90%e5%85%a8%e6%a0%a1%e5%85%ac%e5%85%b1%e5%8d%80%e5%9f%9f%e7%92%b0%e5%a2%83%e6%b6%88%e6%af%92%e5%85%ac%e5%91%8a%e3%80%91/ | N55: 許慧君
A56: =TRUE() | B56: 其他 | D56: 46125 | E56: 115.04.20(星期一)清洗健雄館1-10樓窗台 | F56: 健雄館一樓靠中大湖安全門(電梯旁)暫停開放! 請靠近窗台之房間使用者，當天請務必關上窗戶，以免汙水潑入室內，不便之處請見諒。 一樓104技佐辦公室 二樓206物理系學會 三樓306實驗物理實驗室 四樓406離子佈植實驗室 五樓506-1低溫物理實驗室 六樓624研究室 七樓724研討室 八樓822.824 九樓914 十樓1012 | M56: https://www.phy.ncu.edu.tw/news/115-04-20%e6%98%9f%e6%9c%9f%e4%b8%80%e6%b8%85%e6%b4%97%e5%81%a5%e9%9b%84%e9%a4%a81-10%e6%a8%93%e7%aa%97%e5%8f%b0/ | N56: 許慧君
A57: =TRUE() | B57: 其他 | D57: 46125 | E57: 失物招領(115.04.13) | F57: 有遺失下列物品者，請於115.04.30前至物理系辦(S4-629)認領! | M57: https://www.phy.ncu.edu.tw/news/%e5%a4%b1%e7%89%a9%e6%8b%9b%e9%a0%98115-04-13/ | N57: 許慧君
A58: =TRUE() | B58: 演講 | D58: 46119 | E58: Colloquium_20260414_Quantum Information Perspectives on Non-Hermitian Quantum Systems | F58: Colloquium_20260414Download | G58: Colloquium_20260414 | H58: https://www.phy.ncu.edu.tw/wp-content/uploads/2026/04/Colloquium_20260414.pdf | I58: Download | J58: https://www.phy.ncu.edu.tw/wp-content/uploads/2026/04/Colloquium_20260414.pdf | M58: https://www.phy.ncu.edu.tw/news/colloquium_20260414_quantum-information-perspectives-on-non-hermitian-quantum-systems/ | N58: 許慧君
A59: =TRUE() | B59: 其他 | D59: 46119 | E59: 自主學習微課程「高能粒子動力學與立方衛星任務」 | F59: 本課程由中央大學天文研究所與臺灣太空科學聯盟共同開設，內容涵蓋太空中高能粒子的來源與動力學，並結合立方衛星與深空探測任務相關應用，由美國科羅拉多大學博爾德分校（LASP）李炘璘教授、中央大學葉永烜教授、楊雅惠教授，以及淡江大學汪愷悌教授共同授課。 課程資訊與報名方式請參考： https://twspaceunion.org/epd-course-2026/ | G59: https://twspaceunion.org/epd-course-2026/ | H59: https://twspaceunion.org/epd-course-2026/ | M59: https://www.phy.ncu.edu.tw/news/%e8%87%aa%e4%b8%bb%e5%ad%b8%e7%bf%92%e5%be%ae%e8%aa%b2%e7%a8%8b%e3%80%8c%e9%ab%98%e8%83%bd%e7%b2%92%e5%ad%90%e5%8b%95%e5%8a%9b%e5%ad%b8%e8%88%87%e7%ab%8b%e6%96%b9%e8%a1%9b%e6%98%9f%e4%bb%bb%e5%8b%99/ | N59: 許慧君
A60: =TRUE() | B60: 演講 | D60: 46119 | E60: 【聯電講座】AI與半導體線上分享 | F60: 各位同學 👋 如果有一場講座，可以讓你用 50分鐘看懂 AI 在半導體怎麼用，還能順便抽一組電競裝備，你會不會想參加？👇 👩‍💻 聯電線上講座｜AI與半導體的精彩碰撞 📌 活動資訊 主題｜AI與半導體的精彩碰撞 時間｜4/29（二）12:10–13:00 形式｜線上直播 🍱 午餐時間輕鬆參加（有手機TEAMS就可以上線、不用跑場） 🎤 聯電智慧數位發展處主管親自分享 👉 AI如何實際應用在製造現場 👉 工程師真實職涯發展 🎁 參加到最後直接抽（真的實用） 🎯 參加對象 理工相關科系在學學生 （PTP優先名額｜非PTP亦可報名，名額有限） 🎁 參加好康 👉 女力進化獎：AUKEY 100W行動電源（可充筆電）(市值超過2千元) 👉 工程人必備獎：4K無線電競滑鼠(市值超過3千元) 👉 裝備升級獎：羅技無線機械式電競鍵盤 (市值超過5千元 ) 🚀 還等什麼？現在就報名，提前卡位你的科技職涯未來 👉 更多詳情及報名連結：https://forms.gle/YJpuAKJXkU6cZVCi7 | G60: https://forms.gle/YJpuAKJXkU6cZVCi7 | H60: https://forms.gle/YJpuAKJXkU6cZVCi7 | M60: https://www.phy.ncu.edu.tw/news/%e3%80%90%e8%81%af%e9%9b%bb%e8%ac%9b%e5%ba%a7%e3%80%91ai%e8%88%87%e5%8d%8a%e5%b0%8e%e9%ab%94%e7%b7%9a%e4%b8%8a%e5%88%86%e4%ba%ab/ | N60: 許慧君
A61: =TRUE() | B61: 其他 | D61: 46119 | E61: 物理學系分機通訊錄1150407 | F61: 物理系通訊錄Download | G61: 物理系通訊錄 | H61: https://www.phy.ncu.edu.tw/wp-content/uploads/2026/04/物理系通訊錄.pdf | I61: Download | J61: https://www.phy.ncu.edu.tw/wp-content/uploads/2026/04/物理系通訊錄.pdf | M61: https://www.phy.ncu.edu.tw/news/%e7%89%a9%e7%90%86%e5%ad%b8%e7%b3%bb%e5%88%86%e6%a9%9f%e9%80%9a%e8%a8%8a%e9%8c%841150407/ | N61: 許慧君
A62: =TRUE() | B62: 其他 | D62: 46115 | E62: 【資安宣導】115年度社交工程演練將於4月啟動，防範惡意釣魚信件請提高警覺！ | F62: 一年一度的教育部社交工程演練將於本月（4月）至 12 月期間辦理。教育部將不定期發送各種測試信件，以檢視全校人員的資安防範意識。 預防防護「三不原則」 這類惡意信件通常會夾帶不明連結或附檔。收到可疑信件時，請大家務必保持冷靜。 重中之重：只要不確定信件來源或標題有疑慮，請直接「勾選後刪除」，絕對不要點開！ 若必須確認信件內容，請遵循以下原則： 不輕易點擊連結： 將滑鼠游標停留在連結上方（先不要點擊），觀察瀏覽器左下角顯示的真實網址是否為學校官方網域（ncu.edu.tw）。 不隨便下載附件： 未經確認來源的附檔極可能夾帶惡意程式，請勿輕易開啟。 絕不在不明網頁輸入帳密： 學校絕對不會透過一封信件內的連結，強迫您登入並輸入密碼來「解鎖帳號」或「擴充容量」。 常見釣魚信件標題案例 本次演練將模擬駭客常用的手法，主題涵蓋八卦、休閒、保健、財經、時事等類型。以下整理 10 種常見的標題案例，請特別留意： 請閱讀：NCU重要通知 (年初真實假冒案例) 【資訊中心通知】您的 NCU WebMail 信箱容量已滿，請立即登入擴充！ 【人事室】115年度教職員工薪俸調整方案與個人明細表，請下載附件查閱。 【財政部】您有一筆綜合所得稅退稅即將到期，請點擊連結完成線上申報。 【好康分享】辛巴克/超商 歡慶週年買一送一電子優惠券，限量發送中！ 【健康快訊】最新醫學證實：每天這樣做，心血管疾病風險大幅降低 50%！ 【秘辛爆料】本校某系所主管與廠商私下交涉完整錄音檔流出！ 【圖書館】您的借閱書籍已嚴重逾期，即將產生高額滯納金，請登入確認。 【網購客服】您的包裹因地址標示不清無法投遞，請重新輸入配送資訊。 【私密外流】Dcard瘋傳！本校某系男女同學深夜火辣互動影片完整版！ | G62: ncu.edu.tw | H62: http://ncu.edu.tw/ | M62: https://www.phy.ncu.edu.tw/news/%e3%80%90%e8%b3%87%e5%ae%89%e5%ae%a3%e5%b0%8e%e3%80%91115%e5%b9%b4%e5%ba%a6%e7%a4%be%e4%ba%a4%e5%b7%a5%e7%a8%8b%e6%bc%94%e7%b7%b4%e5%b0%87%e6%96%bc4%e6%9c%88%e5%95%9f%e5%8b%95%ef%bc%8c%e9%98%b2/ | N62: 許慧君
A63: =TRUE() | B63: 其他 | D63: 46113 | E63: 停水公告 / Water Outage Notice 4 月 2 日（四）13:00–17:00 | F63: 📢 停水公告 / Water Outage Notice 本館 1–5 樓地下水停水施工 時間：115 年 4 月 2 日（四）13:00–17:00 施工期間，1–5 樓男女廁所暫停使用，請至 6–10 樓廁所使用。 如因施工狀況可能延長停水時間，若提前施工完畢將立即開放使用。 造成不便，敬請見諒。 Water supply for floors 1–5 will be suspended due to construction. Date & Time: April 2 (Thu), 13:00–17:00 During this period, restrooms on floors 1–5 will be temporarily closed. Please use the restrooms on floors 6–10. The outage may be extended depending on construction progress. If the work is completed earlier, water supply will be restored immediately. We apologize for any inconvenience caused. | M63: https://www.phy.ncu.edu.tw/news/%e5%81%9c%e6%b0%b4%e5%85%ac%e5%91%8a-water-outage-notice-4-%e6%9c%88-2-%e6%97%a5%ef%bc%88%e5%9b%9b%ef%bc%891300-1700/ | N63: 許慧君
A64: =TRUE() | B64: 招生 | C64: 高中生 | D64: 46113 | E64: 115學年度大學申請入學第二階段指定項目甄試通知及報名資訊 | F64: 115學年度大學申請入學第二階段指定項目甄試通知函已於115年4月1日以掛號寄出，敬請注意收件。 如於考試前未收到通知函，可直接參考附件 (內容與紙本相同)。本校招生組另以簡訊通知，敬請留意！ 二階甄試報名： (1) 甄試繳費：4/30上午9:00 ~ 5/5下午3:30。 (2) 審查資料上傳：4/30 ~ 5/5每日9:00~21:00。 二階指定項目甄試通知 二階報名及繳費資訊 二階面試時間申請表 | G64: 二階指定項目甄試通知 | H64: https://www.phy.ncu.edu.tw/wp-content/uploads/2026/04/115申請入學-指定項目甄試函網頁.pdf | I64: 二階報名及繳費資訊 | J64: https://www.phy.ncu.edu.tw/wp-content/uploads/2026/04/115申請入學_報名與繳費通知單.pdf | K64: 二階面試時間申請表 | L64: https://www.phy.ncu.edu.tw/wp-content/uploads/2026/04/115申請入學_面試時間申請表.pdf | M64: https://www.phy.ncu.edu.tw/news/115%e5%ad%b8%e5%b9%b4%e5%ba%a6%e5%a4%a7%e5%ad%b8%e7%94%b3%e8%ab%8b%e5%85%a5%e5%ad%b8%e7%ac%ac%e4%ba%8c%e9%9a%8e%e6%ae%b5%e6%8c%87%e5%ae%9a%e9%a0%85%e7%9b%ae%e7%94%84%e8%a9%a6%e9%80%9a%e7%9f%a5/ | N64: 吳菁穗
A65: =TRUE() | B65: 演講 | D65: 46113 | E65: Colloquium_20260407_Quantum Walk Finds a Way for GKP!! | F65: Colloquium_20260407Download | G65: Colloquium_20260407 | H65: https://www.phy.ncu.edu.tw/wp-content/uploads/2026/04/Colloquium_20260407.pdf | I65: Download | J65: https://www.phy.ncu.edu.tw/wp-content/uploads/2026/04/Colloquium_20260407.pdf | M65: https://www.phy.ncu.edu.tw/news/colloquium_20260407_quantum-walk-finds-a-way-for-gkp/ | N65: 許慧君
A66: =TRUE() | B66: 其他 | D66: 46113 | E66: 【施工公告】天文所10樓4/13（一）上午9點-13點大型機器搬運及安裝工程 | F66: 2026/04/13（一）上午9點～中午13點，天文所將進行一米望遠鏡鍍鏡機進場安裝於10樓光學實驗室。因機器重量、體積龐大，安裝期間貨梯（1&10樓）及10樓通道需要淨空，並預計於 10樓通道暫放大型工作桌及設備，造成您的不便，敬請見諒。 Graduate Institute of Astronomy will move and install large machine on April 13, 2026. The freight elevator on the 1st and 10th floors will be in use for moving items. Please do not place any items in the space in front of the elevators. Also keep the 10th-floor corridor clear. Thank you. | M66: https://www.phy.ncu.edu.tw/news/%e3%80%90%e6%96%bd%e5%b7%a5%e5%85%ac%e5%91%8a%e3%80%91%e5%a4%a9%e6%96%87%e6%89%8010%e6%a8%934-13%ef%bc%88%e4%b8%80%ef%bc%89%e4%b8%8a%e5%8d%889%e9%bb%9e-13%e9%bb%9e%e5%a4%a7%e5%9e%8b%e6%a9%9f%e5%99%a8/ | N66: 許慧君
A67: =TRUE() | B67: 其他 | D67: 46112 | E67: 二樓男女廁所暫停開放 | F67: 本館二樓男女廁所水源開關故障，暫停開放使用，請改至一樓或三樓廁所，造成不便，敬請見諒，謝謝。🚧 | M67: https://www.phy.ncu.edu.tw/news/%e4%ba%8c%e6%a8%93%e7%94%b7%e5%a5%b3%e5%bb%81%e6%89%80%e6%9a%ab%e5%81%9c%e9%96%8b%e6%94%be/ | N67: 許慧君
A68: =TRUE() | B68: 其他 | D68: 46111 | E68: 115/04/21(二)10點 大三UCAN共通職能後測解析 | F68: 大三UCAN共通職能班級後測解析： 時間 ：2026/04/21(二) 10:00-12:00 地點：健雄館S4- 717 講師：四季職涯發展學院的王思涵老師 https://fourseasoncareer.com/career-team/janice/ 施測及解析對象：學號112開頭之大三學生 職涯中心將會在活動前寄信通知學生事先完成線上職能診斷。 全程參加者將提供 1.午餐一份； 2.生活知能(自我探索與生涯規劃學習)時數2小時。 請於2026/04/14(二)前完成線上報名以便統計人數。 報名網址：https://forms.gle/KpFbTgV83wAUAkbM6 | G68: https://fourseasoncareer.com/career-team/janice/ | H68: https://fourseasoncareer.com/career-team/janice/ | I68: https://forms.gle/KpFbTgV83wAUAkbM6 | J68: https://forms.gle/KpFbTgV83wAUAkbM6 | M68: https://www.phy.ncu.edu.tw/news/115-04-21%e4%ba%8c10%e9%bb%9e-%e5%a4%a7%e4%b8%89ucan%e5%85%b1%e9%80%9a%e8%81%b7%e8%83%bd%e5%be%8c%e6%b8%ac%e8%a7%a3%e6%9e%90/ | N68: 吳菁穗
A69: =TRUE() | B69: 其他 | D69: 46108 | E69: 失物招領(115.03.27) | F69: 有遺失下列物品者，請於115.04.30前至物理系辦(S4-629)認領! | M69: https://www.phy.ncu.edu.tw/news/%e5%a4%b1%e7%89%a9%e6%8b%9b%e9%a0%98115-03-27/ | N69: 許慧君
A70: =TRUE() | B70: 其他 | D70: 46107 | E70: 【總務處公告】1150328地下水停水公告 | F70: 國立中央大學停水公告 事由：校區4號地下水水塔排水閘閥漏水搶修 停水日期：115/03/28(六) 停水時間：08:00-17:00 地下水停水區域： 男9AB(含九餐)、12舍、車庫、資源回收場、中大會館、國鼎圖書館、曦望居、管理二館(含一樓餐廳)、志希館(含鬆餅屋)、科二、三、四、五館、理學院教學館(科思創)、鴻經館、綜教館、客家學院、國鼎光電大樓、依仁堂(含週圍場地) 、中大國民運動中心、羽球館、室內游泳池、大型力學實驗室、風洞實驗室、機械館、機電實驗室、鑄造廠、環工/化工館、太遙中心、研究中心二期、雷達站、大氣環境實驗室、工五館A、B(含增建)、C棟、松苑餐廳、產學營運中心、單一、二、四舍、後門警衛室，教學研究綜合大樓。 (各大樓原則皆備有地下蓄水池，停水後仍有蓄水池水源可供使用) ※不便之處敬祈見諒，提早施工完畢後將提早供水，如遇有特殊困難亦可能延緩恢復供水。 施工單位：京融水電工程有限公司 鄭先生0932093643 承辦單位：營繕組 吳先生03-4227151#57320 總務處 啟 | M70: https://www.phy.ncu.edu.tw/news/%e3%80%90%e7%b8%bd%e5%8b%99%e8%99%95%e5%85%ac%e5%91%8a%e3%80%911150328%e5%9c%b0%e4%b8%8b%e6%b0%b4%e5%81%9c%e6%b0%b4%e5%85%ac%e5%91%8a/ | N70: 許慧君
A71: =TRUE() | B71: 演講 | D71: 46105 | E71: Colloquium_20260331_Harnessing Plasmas for Extreme Photonics and Quantum Optics | F71: Colloquium_20260331Download | G71: Colloquium_20260331 | H71: https://www.phy.ncu.edu.tw/wp-content/uploads/2026/03/Colloquium_20260331.pdf | I71: Download | J71: https://www.phy.ncu.edu.tw/wp-content/uploads/2026/03/Colloquium_20260331.pdf | M71: https://www.phy.ncu.edu.tw/news/colloquium_20260331_harnessing-plasmas-for-extreme-photonics-and-quantum-optics/ | N71: 許慧君
A72: =TRUE() | B72: 其他 | D72: 46105 | E72: 【總務處公告】115年高壓檢驗維護停電公告 | F72: 115年高壓檢驗維護停電公告Download | G72: 115年高壓檢驗維護停電公告 | H72: https://www.phy.ncu.edu.tw/wp-content/uploads/2026/03/115年高壓檢驗維護停電公告.pdf | I72: Download | J72: https://www.phy.ncu.edu.tw/wp-content/uploads/2026/03/115年高壓檢驗維護停電公告.pdf | M72: https://www.phy.ncu.edu.tw/news/%e3%80%90%e7%b8%bd%e5%8b%99%e8%99%95%e5%85%ac%e5%91%8a%e3%80%91115%e5%b9%b4%e9%ab%98%e5%a3%93%e6%aa%a2%e9%a9%97%e7%b6%ad%e8%ad%b7%e5%81%9c%e9%9b%bb%e5%85%ac%e5%91%8a/ | N72: 許慧君
A73: =TRUE() | B73: 其他 | D73: 46104 | E73: 115年7月25,26日,8月1日清洗校區總水塔停水公告 | F73: 國立中央大學 清洗校區總水塔停水公告 事由：為維護用水安全將進行供水系統水塔清洗工程，定於115年07月25、26日、08月01日清洗水塔，敬請用戶儲水備用。 第1號水塔停水時間：115年07月25日(六) 09：00至19：00 地下水停水範圍：女1、2、3、4、14舍(含郵局、地下室賣場)、男3、5、6、7(含七餐)、11(含敦煌書局、好視康眼鏡、美髮部、洗衣部)、13舍、國際學生宿舍、志道樓、工程一館(含品保中心)、電機一、二、三館、科一館、總圖書館、中正圖書館、游藝館、據德樓、大講堂、文一、二、三館、行政大樓、前門警衛室、學生自主學習中心。 第3號水塔停水時間：115年07月26日(日) 09：00至19：00 自來水停水範圍：全校自來水停水(含中大新村一、二、三區) 第4號水塔停水時間：115年08月01日(六) 09：00至19：00 地下水停水範圍：男9AB(含九餐)、12舍、車庫、資源回收場、中大會館、國鼎圖書館、曦望居、管理二館(含一樓餐廳)、志希館(含鬆餅屋)、科二、三、四、五館、理學院教學館(科思創)、鴻經館、綜教館、客家學院、國鼎光電大樓、依仁堂(含周圍場地)、中大國民運動中心、羽球館、室內游泳池、大型力學實驗室、風洞實驗室、機械館、機電實驗室、鑄造廠、環工/化工館、太遙中心、研究中心二期、雷達站、大氣環境實驗室、工五館A、B(含增建)、C棟、松苑餐廳、產學營運中心、單一、二、四舍、後門警衛室，教學研究綜合大樓、電機一、二、三館。 一、各大樓原則皆備有蓄水池，停水後仍有蓄水池水源可供使用。 二、倘遇雨天或特殊原因發生致無法工作時，可能取消施工，惟待下次清洗日期決定後，再行公告。 三、不便之處敬祈見諒，提早清洗完畢後將提早供水，如遇有特殊困難亦可能延緩恢復供水。 四、為施作安全，1.3.4號水塔電源及緊急發電機將一併關閉。 施工廠商：五福環境整美有限公司 聯絡電話：莊小姐0927-882918 營繕組電話：03-4227151#57320 總務處 啟 | M73: https://www.phy.ncu.edu.tw/news/115%e5%b9%b47%e6%9c%882526%e6%97%a58%e6%9c%881%e6%97%a5%e6%b8%85%e6%b4%97%e6%a0%a1%e5%8d%80%e7%b8%bd%e6%b0%b4%e5%a1%94%e5%81%9c%e6%b0%b4%e5%85%ac%e5%91%8a/ | N73: 許慧君
A74: =TRUE() | B74: 招生 | D74: 46100 | E74: 115學年度碩士班考試入學複試錄取名單 | F74: https://admission.ncu.edu.tw/zh-TW/article/2026-03-19%2013:18:38/9 正取生:成績單、報到通知單於3/19以掛號寄至通訊地址。 備取生:成績單於3/19以掛號寄至通訊地址。 115學年度碩士班考試入學招生入學報到階段查詢 https://cis.ncu.edu.tw/ExamRegister/checkin?activityNo=189 | G74: https://admission.ncu.edu.tw/zh-TW/article/2026-03-19%2013:1 | H74: https://admission.ncu.edu.tw/zh-TW/article/2026-03-19%2013:18:38/9 | I74: https://cis.ncu.edu.tw/ExamRegister/checkin?activityNo=189 | J74: https://cis.ncu.edu.tw/ExamRegister/checkin?activityNo=189 | M74: https://www.phy.ncu.edu.tw/news/115%e5%ad%b8%e5%b9%b4%e5%ba%a6%e7%a2%a9%e5%a3%ab%e7%8f%ad%e8%80%83%e8%a9%a6%e5%85%a5%e5%ad%b8%e8%a4%87%e8%a9%a6%e9%8c%84%e5%8f%96%e5%90%8d%e5%96%ae/ | N74: 許慧君
A75: =TRUE() | B75: 考試 | D75: 46099 | E75: 新版博碩論文典藏系統正式上線，歡迎報名3/24(二) 10:10線上講習會 | F75: 新版的論文系統已正式上線，為了讓大家快速了解新系統各項上傳流程與注意事項， 將於民國115年3月24日(二)10:10-11:00開設一場線上講習會， 報名網址如下：https://cis.ncu.edu.tw/iNCU/messageNotice/activityManagement/activity/1534 亦提供中英文版的網頁與教學影片，歡迎參考： 1.中文版文字說明與教學影片： https://rapid.lib.ncu.edu.tw/libweek/guide/04-3.html 2.英文版文字說明與教學影片： https://rapid.lib.ncu.edu.tw/libweek/guide/en/04-3.html 國立中央大學圖書館 推廣服務組敬上 ncu57407@ncu.edu.tw (03)422-7151#57407 | G75: https://cis.ncu.edu.tw/iNCU/messageNotice/activityManagement | H75: https://cis.ncu.edu.tw/iNCU/messageNotice/activityManagement/activity/1534 | I75: https://rapid.lib.ncu.edu.tw/libweek/guide/04-3.html | J75: https://rapid.lib.ncu.edu.tw/libweek/guide/04-3.html | K75: https://rapid.lib.ncu.edu.tw/libweek/guide/en/04-3.html | L75: https://rapid.lib.ncu.edu.tw/libweek/guide/en/04-3.html | M75: https://www.phy.ncu.edu.tw/news/%e6%96%b0%e7%89%88%e5%8d%9a%e7%a2%a9%e8%ab%96%e6%96%87%e5%85%b8%e8%97%8f%e7%b3%bb%e7%b5%b1%e6%ad%a3%e5%bc%8f%e4%b8%8a%e7%b7%9a%ef%bc%8c%e6%ad%a1%e8%bf%8e%e5%a0%b1%e5%90%8d3-24%e4%ba%8c-1010/ | N75: 許慧君
A76: =TRUE() | B76: 演講 | D76: 46098 | E76: Colloquium_20260324_Probing the Physics of Living Matter via Single-Molecule and Single-Cell Dynamic Force Spectroscopy | F76: Colloquium_20260324Download | G76: Colloquium_20260324 | H76: https://www.phy.ncu.edu.tw/wp-content/uploads/2026/03/Colloquium_20260324.pdf | I76: Download | J76: https://www.phy.ncu.edu.tw/wp-content/uploads/2026/03/Colloquium_20260324.pdf | M76: https://www.phy.ncu.edu.tw/news/colloquium_20260324_probing-the-physics-of-living-matter-via-single-molecule-and-single-cell-dynamic-force-spectroscopy/ | N76: 許慧君
A77: =TRUE() | B77: 獎學金 | D77: 46098 | E77: 115年度「國科會博士生研究獎學金」獲獎博士生名單 | F77: 獲獎年月 姓名 113-2 艾宗瀚 114-2 盧比奧 附件1 國科會甄選類試辦方案Download | G77: 附件1 國科會甄選類試辦方案 | H77: https://www.phy.ncu.edu.tw/wp-content/uploads/2026/03/附件1-國科會甄選類試辦方案.pdf | I77: Download | J77: https://www.phy.ncu.edu.tw/wp-content/uploads/2026/03/附件1-國科會甄選類試辦方案.pdf | M77: https://www.phy.ncu.edu.tw/news/115%e5%b9%b4%e5%ba%a6%e3%80%8c%e5%9c%8b%e7%a7%91%e6%9c%83%e5%8d%9a%e5%a3%ab%e7%94%9f%e7%a0%94%e7%a9%b6%e7%8d%8e%e5%ad%b8%e9%87%91%e3%80%8d%e7%8d%b2%e7%8d%8e%e5%8d%9a%e5%a3%ab%e7%94%9f%e5%90%8d/ | N77: 許慧君
A78: =TRUE() | B78: 其他 | D78: 46092 | E78: S4-717暫停開放公告 | F78: 4/7(二)10-14理學院EMI修課學生交流會 5/8(五)09-14理學院第三屆學生英文演說比賽 5/20(三)物理系個人申請 05/21(四)理學院學士班個人申請 6/3(三)理學院EMI助教交流會 6/12(五)理學院外籍生交流會 非活動相關者請勿進入 學生自習請改至 721 讀書室 討論活動請多加利用各樓層電梯前討論區 及 627紀念書房 造成不便，敬請見諒，謝謝合作。 | M78: https://www.phy.ncu.edu.tw/news/s4-717%e6%9a%ab%e5%81%9c%e9%96%8b%e6%94%be%e5%85%ac%e5%91%8a-6/ | N78: 許慧君
A79: =TRUE() | B79: 獎學金 | D79: 46092 | E79: 114-2物理學系陳滌清何崇媺紀念基金會獎學金得獎名單公告 | F79: 恭喜以下同學獲獎! 請獲獎同學到系辦領取通知，並請留意email相關領獎注意事項。 得獎名單(以學號排序) 優秀學生獎助 莊沂恩 112202027 大學部 出國交流 林志霖 111202024 大學部 出國交流 邱柏勳 111202528 大學部 出國交流 周禹璇 111222018 博士班 出國交流 廖明軒 114282003 博士班 國際會議 温焌忠 111202010 大學部 國際會議 洪琳喬 111202509 大學部 國際會議 陳佳妍 113222018 碩士班 國際會議 汪師緯 113222034 碩士班 國際會議 廖明軒 114282003 博士班 國立中央大學物理學系陳滌清何崇媺紀念基金會獎學金辦法1140218系務會議通過Download | G79: 國立中央大學物理學系陳滌清何崇媺紀念基金會獎學金辦法1140218系務會議通過 | H79: https://www.phy.ncu.edu.tw/wp-content/uploads/2026/03/國立中央大學物理學系陳滌清何崇媺紀念基金會獎學金辦法1140218系務會議通過.pdf | I79: Download | J79: https://www.phy.ncu.edu.tw/wp-content/uploads/2026/03/國立中央大學物理學系陳滌清何崇媺紀念基金會獎學金辦法1140218系務會議通過.pdf | M79: https://www.phy.ncu.edu.tw/news/114-2%e7%89%a9%e7%90%86%e5%ad%b8%e7%b3%bb%e9%99%b3%e6%bb%8c%e6%b8%85%e4%bd%95%e5%b4%87%e5%aa%ba%e7%b4%80%e5%bf%b5%e5%9f%ba%e9%87%91%e6%9c%83%e7%8d%8e%e5%ad%b8%e9%87%91%e5%be%97%e7%8d%8e%e5%90%8d/ | N79: 許慧君
A80: =TRUE() | B80: 獎學金 | D80: 46092 | E80: 114-2物理學系上詮光纖獎學金得獎名單 | F80: 恭喜以下同學獲獎! 請獲獎同學到系辦領取通知，並請留意email相關領獎注意事項。 得獎名單(以學號排序) 出國交流 莎塔 111282606 博士班 出國交流 陳佳妍 113222018 碩士班 國際會議 楊苡若 111202508 大學部 研究傑出獎助 黃俊智 113222031 碩士班 國立中央大學物理學系上詮光纖獎學金辦法(FOCI Scholarship Application Procedure)1120321系務會議通過Download | G80: 國立中央大學物理學系上詮光纖獎學金辦法(FOCI Scholarship Application Procedure)1 | H80: https://www.phy.ncu.edu.tw/wp-content/uploads/2026/03/國立中央大學物理學系上詮光纖獎學金辦法FOCI-Scholarship-Application-Procedure1120321系務會議通過.pdf | I80: Download | J80: https://www.phy.ncu.edu.tw/wp-content/uploads/2026/03/國立中央大學物理學系上詮光纖獎學金辦法FOCI-Scholarship-Application-Procedure1120321系務會議通過.pdf | M80: https://www.phy.ncu.edu.tw/news/114-2%e7%89%a9%e7%90%86%e5%ad%b8%e7%b3%bb%e4%b8%8a%e8%a9%ae%e5%85%89%e7%ba%96%e7%8d%8e%e5%ad%b8%e9%87%91%e5%be%97%e7%8d%8e%e5%90%8d%e5%96%ae/ | N80: 許慧君
A81: =TRUE() | B81: 演講 | D81: 46092 | E81: Colloquium_20260317_New platforms for quantum technology | F81: Colloquium_20260317Download | G81: Colloquium_20260317 | H81: https://www.phy.ncu.edu.tw/wp-content/uploads/2026/03/Colloquium_20260317.pdf | I81: Download | J81: https://www.phy.ncu.edu.tw/wp-content/uploads/2026/03/Colloquium_20260317.pdf | M81: https://www.phy.ncu.edu.tw/news/colloquium_20260317_new-platforms-for-quantum-technology/ | N81: 許慧君
A82: =TRUE() | B82: 其他 | D82: 46091 | E82: 115年3月14日至115年3月23日科四館、科五館前局部地坪整修工程 施工公告 | F82: 施工公告 一、工程名稱：科四館、科五館前局部地坪整修工程 二、施工期間：115年3月14日至115年3月23日(預定10個工作日，遇雨順延一週，固定以週六為第一日施工日，辦理打除作業) 三、施工地點：科四館、科五館前 四、說 明： (一)施工期間附近車格無法停車，將以交通錐單點設置，敬請配合請勿停車。 (二)施工期間有粉塵、噪音現象。 (三)室外工程倘遇雨無法施工，則工期順延，不另公告。 (四)施工期間造成不便之處，敬請 見諒!! 施工廠商︰福安土木包工業 負 責 人：簡先生 電話：0928-873115 總務處 營繕組 敬啟 | M82: https://www.phy.ncu.edu.tw/news/115%e5%b9%b43%e6%9c%8814%e6%97%a5%e8%87%b3115%e5%b9%b43%e6%9c%8823%e6%97%a5%e7%a7%91%e5%9b%9b%e9%a4%a8%e3%80%81%e7%a7%91%e4%ba%94%e9%a4%a8%e5%89%8d%e5%b1%80%e9%83%a8%e5%9c%b0%e5%9d%aa%e6%95%b4/ | N82: 許慧君
A83: =TRUE() | B83: 獎學金 | D83: 46091 | E83: 114-2物理學系德成基金會獎學金得獎名單 | F83: 恭喜以下同學獲獎! 獲獎同學請留意得獎email通知相關注意事項 得獎名單以學號排序 李侑哲 112202024 許宏瑋 112202512 李承駿 112202517 國立中央大學物理學系德成基金會獎學金辦法1120321系務會議通過Download | G83: 國立中央大學物理學系德成基金會獎學金辦法1120321系務會議通過 | H83: https://www.phy.ncu.edu.tw/wp-content/uploads/2026/03/國立中央大學物理學系德成基金會獎學金辦法1120321系務會議通過-1.pdf | I83: Download | J83: https://www.phy.ncu.edu.tw/wp-content/uploads/2026/03/國立中央大學物理學系德成基金會獎學金辦法1120321系務會議通過-1.pdf | M83: https://www.phy.ncu.edu.tw/news/114-2%e7%89%a9%e7%90%86%e5%ad%b8%e7%b3%bb%e5%be%b7%e6%88%90%e5%9f%ba%e9%87%91%e6%9c%83%e7%8d%8e%e5%ad%b8%e9%87%91%e5%be%97%e7%8d%8e%e5%90%8d%e5%96%ae/ | N83: 許慧君
A84: =TRUE() | B84: 計畫 | C84: 獎學金 | D84: 46091 | E84: 教育部114學年度「大專校院學生雙語化學習計畫」出國補助申請審核結果公告 | F84: 恭喜以下同學獲獎(以學號排序) 請獲補助同學留意Email通知，內有經費補助重要訊息。 博士班 110282005 鄧善友 學士班 111202006 蔡子翔 學士班 111202517 朱珈聖 學士班 111202517 朱珈聖 學士班 111202521 陳品毅 博士班 112222016 張辰彬 博士班 113282003 李俊逸 博士班 113282005 張容誌 博士班 114282003 廖明軒 | M84: https://www.phy.ncu.edu.tw/news/%e6%95%99%e8%82%b2%e9%83%a8114%e5%ad%b8%e5%b9%b4%e5%ba%a6%e3%80%8c%e5%a4%a7%e5%b0%88%e6%a0%a1%e9%99%a2%e5%ad%b8%e7%94%9f%e9%9b%99%e8%aa%9e%e5%8c%96%e5%ad%b8%e7%bf%92%e8%a8%88%e7%95%ab%e3%80%8d-2/ | N84: 許慧君
A85: =TRUE() | B85: 演講 | D85: 46084 | E85: Colloquium_20260310_從實驗室到戰場：理工人無痛轉職的3大核心 | F85: Colloquium_20260310Download | G85: Colloquium_20260310 | H85: https://www.phy.ncu.edu.tw/wp-content/uploads/2026/03/Colloquium_20260310.pdf | I85: Download | J85: https://www.phy.ncu.edu.tw/wp-content/uploads/2026/03/Colloquium_20260310.pdf | M85: https://www.phy.ncu.edu.tw/news/colloquium_20260310_%e5%be%9e%e5%af%a6%e9%a9%97%e5%ae%a4%e5%88%b0%e6%88%b0%e5%a0%b4%ef%bc%9a%e7%90%86%e5%b7%a5%e4%ba%ba%e7%84%a1%e7%97%9b%e8%bd%89%e8%81%b7%e7%9a%843%e5%a4%a7%e6%a0%b8%e5%bf%83/ | N85: 許慧君
A86: =TRUE() | B86: 其他 | D86: 46083 | E86: 失物招領(115.03.02) | F86: 有遺失下列物品者，請於115.03.28前至物理系辦(S4-629)認領! | M86: https://www.phy.ncu.edu.tw/news/%e5%a4%b1%e7%89%a9%e6%8b%9b%e9%a0%98115-03-02/ | N86: 許慧君
A87: =TRUE() | B87: 招生 | D87: 46079 | E87: 115學年度碩士班考試入學得參加複試名單 | F87: https://admission.ncu.edu.tw/zh-TW/article/2026-02-26%2012:20:10/9 可參加複試同學:成績單及複試通知單於115.2.26以掛號郵寄至通訊地址。 簡報資料請於115年03月09日(星期一)17:00前Email電子檔至corona@ncu.edu.tw，檔名：【准考證號╴姓名】，當日亦請務必攜帶簡報電子檔以備用。 複試當日，考生可憑複試通知單出校走左側車道，免收停車費，如考生車輛有eTag停車費自動扣款者，出校時須另告知警衛eTag請勿扣款，未告知致扣款者，恕不退費。 115物理系碩士班入學考試複試通知函Download | G87: https://admission.ncu.edu.tw/zh-TW/article/2026-02-26%2012:2 | H87: https://admission.ncu.edu.tw/zh-TW/article/2026-02-26%2012:20:10/9 | I87: 115物理系碩士班入學考試複試通知函 | J87: https://www.phy.ncu.edu.tw/wp-content/uploads/2026/02/115物理系碩士班入學考試複試通知函.pdf | K87: Download | L87: https://www.phy.ncu.edu.tw/wp-content/uploads/2026/02/115物理系碩士班入學考試複試通知函.pdf | M87: https://www.phy.ncu.edu.tw/news/115%e5%ad%b8%e5%b9%b4%e5%ba%a6%e7%a2%a9%e5%a3%ab%e7%8f%ad%e8%80%83%e8%a9%a6%e5%85%a5%e5%ad%b8%e5%be%97%e5%8f%83%e5%8a%a0%e8%a4%87%e8%a9%a6%e5%90%8d%e5%96%ae/ | N87: 許慧君
A88: =TRUE() | B88: 演講 | D88: 46077 | E88: Colloquium_20260303_Effective Shaping and Probing of Antiferromagnetic Order | F88: Colloquium_20260303Download | G88: Colloquium_20260303 | H88: https://www.phy.ncu.edu.tw/wp-content/uploads/2026/02/Colloquium_20260303.pdf | I88: Download | J88: https://www.phy.ncu.edu.tw/wp-content/uploads/2026/02/Colloquium_20260303.pdf | M88: https://www.phy.ncu.edu.tw/news/colloquium_20260303_effective-shaping-and-probing-of-antiferromagnetic-order/ | N88: 許慧君
A89: =TRUE() | B89: 其他 | D89: 46077 | E89: 114學年度第2學期課程教學助教志願調查1150224 | F89: 中央大學物理系公告-114學年度第2學期課程教學助教志願調查 NCU Physics Departmental Notice-2025/2026 Second Semester Teaching Assistant Application Form 物理系研究生欲申請擔任課程教學助教者，請於115年2月28日前填寫『課程教學助教志願表』(https://forms.gle/ZbTYtMT5guR3wpvVA)。 Physics Department graduate students who wish to serve as teaching assistants (TA), please fill in the TA Application Form before Feb 28, 2026 . (https://forms.gle/ZbTYtMT5guR3wpvVA)。 依研究生修業規定，修業期間碩士生至少需擔任一學期（上下學期皆可）課程助教、博士生至少需擔任兩學期（上下學期各一）課程助教，方可畢業。 The Graduate Student’s Course Regulations require master students to serve as TAs for at least one semester (once in either semester), while doctoral students must serve for at least two semesters (once in both semesters) as part of the criteria for graduation. 114-2助教TADownload 國立中央大學物理系研究生獎助學金辦法20210708系務會議通過Download | G89: https://forms.gle/ZbTYtMT5guR3wpvVA | H89: https://forms.gle/ZbTYtMT5guR3wpvVA | I89: https://forms.gle/ZbTYtMT5guR3wpvVA | J89: https://forms.gle/ZbTYtMT5guR3wpvVA | K89: 114-2助教TA | L89: https://www.phy.ncu.edu.tw/wp-content/uploads/2026/02/114-2助教TA-1.pdf | M89: https://www.phy.ncu.edu.tw/news/114%e5%ad%b8%e5%b9%b4%e5%ba%a6%e7%ac%ac2%e5%ad%b8%e6%9c%9f%e8%aa%b2%e7%a8%8b%e6%95%99%e5%ad%b8%e5%8a%a9%e6%95%99%e5%bf%97%e9%a1%98%e8%aa%bf%e6%9f%a51150224/ | N89: 許慧君
A90: =TRUE() | B90: 招生 | C90: 高中生 | D90: 46076 | E90: 115學年度大學申請入學簡章、審查準備指引、二階甄試考生須知 | F90: 115申請入學 簡章、審查準備指引、二階甄試考生須知 已公告 於本校招生資訊網 https://admission.ncu.edu.tw/zh-TW/content/71/12 115申請入學_準備指引_072 物理Download 115申請入學_考生須知_分則_072物理Download | G90: https://admission.ncu.edu.tw/zh-TW/content/71/12 | H90: https://admission.ncu.edu.tw/zh-TW/content/71/12 | I90: 115申請入學_準備指引_072 物理 | J90: https://www.phy.ncu.edu.tw/wp-content/uploads/2026/02/115申請入學_準備指引_072-物理.pdf | K90: Download | L90: https://www.phy.ncu.edu.tw/wp-content/uploads/2026/02/115申請入學_準備指引_072-物理.pdf | M90: https://www.phy.ncu.edu.tw/news/115%e7%94%b3%e8%ab%8b%e5%85%a5%e5%ad%b8%e7%b0%a1%e7%ab%a0%e3%80%81%e5%af%a9%e6%9f%a5%e6%ba%96%e5%82%99%e6%8c%87%e5%bc%95%e3%80%81%e4%ba%8c%e9%9a%8e%e7%94%84%e8%a9%a6%e8%80%83%e7%94%9f%e9%a0%88/ | N90: 吳菁穗
A91: =TRUE() | B91: 其他 | D91: 46066 | E91: 114-2學期註冊繳費重要公告 | F91: 1142註冊繳費公告Download | G91: 1142註冊繳費公告 | H91: https://www.phy.ncu.edu.tw/wp-content/uploads/2026/02/1142註冊繳費公告.pdf | I91: Download | J91: https://www.phy.ncu.edu.tw/wp-content/uploads/2026/02/1142註冊繳費公告.pdf | M91: https://www.phy.ncu.edu.tw/news/114-2%e5%ad%b8%e6%9c%9f%e8%a8%bb%e5%86%8a%e7%b9%b3%e8%b2%bb%e9%87%8d%e8%a6%81%e5%85%ac%e5%91%8a/ | N91: 許慧君
A92: =TRUE() | B92: 其他 | D92: 46065 | E92: 114-2 Graduate Students’ Graduation Procedure of the Physics Department | F92: 物理系研究生畢業離校手續Graduate Students’ Graduation Procedure of the Physics DepartmentDownload 物理系離校系所同意書Graduation Form of the Physics Department of National Central UniversityDownload 1150212公告1142頒發學位證書注意事項Download Graduation School-leaving Questionnaire InstructionsDownload | G92: 物理系研究生畢業離校手續Graduate Students’ Graduation Procedure of the P | H92: https://www.phy.ncu.edu.tw/wp-content/uploads/2026/02/物理系研究生畢業離校手續Graduate-Students-Graduation-Procedure-of-the-Physics-Department-1.pdf | I92: Download | J92: https://www.phy.ncu.edu.tw/wp-content/uploads/2026/02/物理系研究生畢業離校手續Graduate-Students-Graduation-Procedure-of-the-Physics-Department-1.pdf | K92: 物理系離校系所同意書Graduation Form of the Physics Department of Natio | L92: https://www.phy.ncu.edu.tw/wp-content/uploads/2026/02/物理系離校系所同意書Graduation-Form-of-the-Physics-Department-of-National-Central-University-1-1.pdf | M92: https://www.phy.ncu.edu.tw/news/114-2-graduate-students-graduation-procedure-of-the-physics-department/ | N92: 許慧君
A93: =TRUE() | B93: 其他 | D93: 46065 | E93: 114-2物理系研究生畢業離校手續Graduate Students’ Graduation Procedure of the Physics Department | F93: 物理系研究生畢業離校手續Graduate Students’ Graduation Procedure of the Physics DepartmentDownload 物理系離校系所同意書Graduation Form of the Physics Department of National Central UniversityDownload 1150212公告1142頒發學位證書注意事項Download Graduation School-leaving Questionnaire InstructionsDownload 電子論文上傳 https://rapid.lib.ncu.edu.tw/libweek/guide/04-3.html https://www.youtube.com/watch?v=KKbZnJYtnvQ Thesis Upload https://rapid.lib.ncu.edu.tw/libweek/guide/en/04-3.html https://www.youtube.com/watch?v=fUN-PpCkIPQ | G93: 物理系研究生畢業離校手續Graduate Students’ Graduation Procedure of the P | H93: https://www.phy.ncu.edu.tw/wp-content/uploads/2026/02/物理系研究生畢業離校手續Graduate-Students-Graduation-Procedure-of-the-Physics-Department.pdf | I93: Download | J93: https://www.phy.ncu.edu.tw/wp-content/uploads/2026/02/物理系研究生畢業離校手續Graduate-Students-Graduation-Procedure-of-the-Physics-Department.pdf | K93: 物理系離校系所同意書Graduation Form of the Physics Department of Natio | L93: https://www.phy.ncu.edu.tw/wp-content/uploads/2026/02/物理系離校系所同意書Graduation-Form-of-the-Physics-Department-of-National-Central-University-.pdf | M93: https://www.phy.ncu.edu.tw/news/114-2%e7%89%a9%e7%90%86%e7%b3%bb%e7%a0%94%e7%a9%b6%e7%94%9f%e7%95%a2%e6%a5%ad%e9%9b%a2%e6%a0%a1%e6%89%8b%e7%ba%8cgraduate-students-graduation-procedure-of-the-physics-department/ | N93: 許慧君
A94: =TRUE() | B94: 演講 | D94: 46063 | E94: Colloquium_20260224_Polarization Charge Effects in Microwave Heating | F94: Colloquium_20260224Download | G94: Colloquium_20260224 | H94: https://www.phy.ncu.edu.tw/wp-content/uploads/2026/02/Colloquium_20260224.pdf | I94: Download | J94: https://www.phy.ncu.edu.tw/wp-content/uploads/2026/02/Colloquium_20260224.pdf | M94: https://www.phy.ncu.edu.tw/news/colloquium_20260224_polarization-charge-effects-in-microwave-heating/ | N94: 許慧君
A95: =TRUE() | B95: 演講 | D95: 46063 | E95: 114-2 Colloquium | F95: 演講日期(Schedule)演講人(Speaker)職稱/單位(Affiliation)演講題目(Title) 12026/2/24Dr. Li-Chung LiuPostdoctoral Research Fellow Department of Physics, NTUPolarization Charge Effects in Microwave Heating 22026/3/3Prof. Chao-Yao Yang (楊朝堯)Assistant Professor, Fellow of the Higher Education Academy Dept. Materials Science and Engineering, NYCUEffective Shaping and Probing of Antiferromagnetic Order 32026/3/10陳彥穆博士錼創顯示科技股份有限公司 PlayNitride Display Co., Ltd.從實驗室到戰場：理工人無痛轉職的3大核心 42026/3/17Dr. Shayne BennettsAssistant Research Fellow Institute of Atomic and Molecular Sciences, Academia SinicaNew platforms for quantum technology: Towards hybrid atom-nanophotonics and superradiant optical atomic clocks 52026/3/24Prof. Ching-Hwa Kiang (江慶華)Department of Physics & Astronomy, Rice UniversityProbing the Physics of Living Matter via Single-Molecule and Single-Cell Dynamic Force Spectroscopy 62026/3/31Dr. Kenan QuResearch Scholar, Department of Astrophysical Sciences, Princeton UniversityHarnessing Plasmas for Extreme Photonics and Quantum Optics 72026/4/7Prof. Shin-Tza Wu(吳欣澤)Associate Professor, Department of Physics, National Chung-Cheng UniversityAssociate Professor, Department of Physics, National Chung-Cheng University 82026/4/14Dr. Yu-Chin Tzeng (曾郁欽)Research Scholar (Principle Investigator), Center for Theoretical and Computational Physics(CTCP), National Yang Ming Chiao Tung UniversityQuantum Information Perspectives on Non-Hermitian Quantum Systems 92026/4/21Dr. Tetsuya HiraiwaAssociate Research Fellow, Institute of Physics, Academia SinicaNumerical studies of the morphodynamics of dynamic cell assemblies 102026/4/28Dr. Jyh-Long Chern (陳志隆)Formerly Professor, Institute of Electro-Optical Engineering, NCTU Formerly Professor, Department of Physics, NCKUFrom Eikonal to Entanglement: A Unified Framework for Classical and Quantum Photonic Systems 112026/05/05Prof. Jhen-Yong Hong (洪振湧) Department of Physics, Tamkang UniversityRevisiting Magnetic Heterostructures – From Deterministic to Stochastic Spintronics Devices 122026/5/12Dr. Chun-Chia Chen(陳俊嘉)Assistant Research Fellow, Institute of Atomic and Molecular Sciences, Academia SinicaHarnessing Metastable States for Next-Generation Quantum Sensors and Clocks 132026/5/19Prof. Tai Chang Chiang(江台章教授)Professor Emeritus and Research Professor, Department of Physics, University of Illinois at Urbana-Champaign Yushan Fellow, Dept. of Physics, NCUSuperconductivity of topological states induced by proximity and Josephson coupling 142026/5/26Ryota Sakamoto 152026/6/2劉煥祥 諮商心理師 162026/6/9 | G95: Polarization Charge Effects in Microwave Heating | H95: https://www.phy.ncu.edu.tw/news/colloquium_20260224_polarization-charge-effects-in-microwave-heating/ | I95: Effective Shaping and Probing of Antiferromagnetic Order | J95: https://www.phy.ncu.edu.tw/news/colloquium_20260303_effective-shaping-and-probing-of-antiferromagnetic-order/ | K95: 從實驗室到戰場：理工人無痛轉職的3大核心 | L95: https://www.phy.ncu.edu.tw/news/colloquium_20260310_%e5%be%9e%e5%af%a6%e9%a9%97%e5%ae%a4%e5%88%b0%e6%88%b0%e5%a0%b4%ef%bc%9a%e7%90%86%e5%b7%a5%e4%ba%ba%e7%84%a1%e7%97%9b%e8%bd%89%e8%81%b7%e7%9a%843%e5%a4%a7%e6%a0%b8%e5%bf%83/ | M95: https://www.phy.ncu.edu.tw/news/114-2-colloquium/ | N95: 許慧君
A96: =TRUE() | B96: 招生 | D96: 46062 | E96: 『114學年國立中央大學物理學系五年取得學、碩士學位』申請公告 | F96: 物理系五年取得學碩士學位申請表Download 114學年度五年學碩申請公告Download 理學院物理系五年取得學碩士學位推薦辦法1120926系務會議通過Download | G96: 物理系五年取得學碩士學位申請表 | H96: https://www.phy.ncu.edu.tw/wp-content/uploads/2026/02/物理系五年取得學碩士學位申請表.doc | I96: Download | J96: https://www.phy.ncu.edu.tw/wp-content/uploads/2026/02/物理系五年取得學碩士學位申請表.doc | K96: 114學年度五年學碩申請公告 | L96: https://www.phy.ncu.edu.tw/wp-content/uploads/2026/02/114學年度五年學碩申請公告.pdf | M96: https://www.phy.ncu.edu.tw/news/%e3%80%8e114%e5%ad%b8%e5%b9%b4%e5%9c%8b%e7%ab%8b%e4%b8%ad%e5%a4%ae%e5%a4%a7%e5%ad%b8%e7%89%a9%e7%90%86%e5%ad%b8%e7%b3%bb%e4%ba%94%e5%b9%b4%e5%8f%96%e5%be%97%e5%ad%b8%e3%80%81%e7%a2%a9%e5%a3%ab/ | N96: 許慧君
A97: =TRUE() | B97: 其他 | D97: 46055 | E97: 失物招領(115.02.02) | F97: 有遺失下列物品者，請於115.02.28前至物理系辦(S4-629)認領! | M97: https://www.phy.ncu.edu.tw/news/%e5%a4%b1%e7%89%a9%e6%8b%9b%e9%a0%98115-02-02/ | N97: 許慧君
A98: =TRUE() | B98: 其他 | D98: 46055 | E98: 114-2 Physics Department PHD&amp;MA Thesis Defense Notification | F98: 物理系博碩士班學位考試注意事項Physics Department PHD&MA Thesis Defense NotificationDownload | G98: 物理系博碩士班學位考試注意事項Physics Department PHD&MA Thesis Defense Noti | H98: https://www.phy.ncu.edu.tw/wp-content/uploads/2026/02/物理系博碩士班學位考試注意事項Physics-Department-PHDMA-Thesis-Defense-Notification-4.pdf | I98: Download | J98: https://www.phy.ncu.edu.tw/wp-content/uploads/2026/02/物理系博碩士班學位考試注意事項Physics-Department-PHDMA-Thesis-Defense-Notification-4.pdf | M98: https://www.phy.ncu.edu.tw/news/114-2-physics-department-phdma-thesis-defense-notification/ | N98: 許慧君
A99: =TRUE() | B99: 其他 | D99: 46055 | E99: 114-2 Course Credit Exemption and Waiver | F99: 抵免、免修學分之申請時間：新生（含轉學生）應於入學第一學期或第二學期校曆規定時間內辦理。 New students (including the transfer) should complete the procedure during the appointed period according to the school calendar of the first semester or the second semester. 物理學系碩博士班研究生修業辦法Regulation of Course Requirements for Master and PhD Programs 1050615 時間：2/2-3/6 ———————————————————————————————————————————————————————— 申請法規Regulations： *國立中央大學學分抵免辦法(https://pdc.adm.ncu.edu.tw/rule/rule113/13-0-1.pdf) National Central University Course Credit Waiver Guidelines(https://pdc.adm.ncu.edu.tw/eng/rule/NCU_Doc13_0_ed.pdf) *物理學系碩士班研究生學分抵免辦法Regulation of Credit Transfer – the Master Program *物理學系博士班研究生學分抵免辦法Regulation of Credit Transfer – the Ph.D. Programs ———————————————————————————————————————————————————————— 申請表Application Form： 抵免：國立中央大學學生學分抵免申請表Guidelines for Credits Exemption (抵免成功後，會在成績單上出現該課程，且學分數會加入本學籍） 如果是他校及本校非同系所畢業之研究所新生入學辦理抵免，須多填寫『國立中央大學學生學分抵免申請修讀研究所學分證明』。 免修：物理學系研究生課程免修申請表Application Form for the Waiver of the Courses （免修成功後，表該課程無需再修，但學分數未計入本學籍，亦不會出現在成績單上） 課程抵必修課(限博士生)-物理學系博士生選修外系課程抵PH開頭課程申請表 (如博士班修業辦法註2: 如因研究所需，學生經指導教授同意後，由課程委員會審核通過，可修習本校及台聯大博士班(含碩博同修)課程，以減少上述 PH5、PH6、PH7、PH8、PHT 開頭課程之選修要求。(至多 A 組減少 2 門、B 組減少 2 門、C 組減少 2 門、D 組減少 4 門)。)( With agreement from his/her advisor and the approval of the Department Course Committee, a student taking the PhD courses offered by the University System of Taiwan can reduce the requirement of PH5, PH6, PH7,PH8, and PHT optional courses up to two for Groups A, B, and C and up to four for Group D.) | G99: 物理學系碩博士班研究生修業辦法Regulation of Course Requirements for Master | H99: https://www.phy.ncu.edu.tw/wp-content/uploads/2021/01/%E5%9C%8B%EF%A7%B7%E4%B8%AD%E5%A4%AE%E5%A4%A7%E5%AD%B8%E7%89%A9%EF%A7%A4%E5%AD%B8%E7%B3%BB%E7%A2%A9%E3%80%81%E5%8D%9A%E5%A3%AB%E7%8F%AD%E7%A0%94%E7%A9%B6%E7%94%9F%E4%BF%AE%E6%A5%AD%E8%BE%A6%E6%B3%951050615%E6%95%99%E5%8B%99%E6%9C%83%E8%AD%B0%E9%80%9A%E9%81%8E.pdf | I99: https://pdc.adm.ncu.edu.tw/rule/rule113/13-0-1.pdf | J99: https://pdc.adm.ncu.edu.tw/rule/rule113/13-0-1.pdf | K99: https://pdc.adm.ncu.edu.tw/eng/rule/NCU_Doc13_0_ed.pdf | L99: https://pdc.adm.ncu.edu.tw/eng/rule/NCU_Doc13_0_ed.pdf | M99: https://www.phy.ncu.edu.tw/news/114-2-course-credit-exemption-and-waiver/ | N99: 許慧君
A100: =TRUE() | B100: 其他 | D100: 46055 | E100: 114-2 物理系博碩士班學位考試注意事項Physics Department PHD&amp;MA Thesis Defense Notification | F100: 物理系博碩士班學位考試注意事項Physics Department PHD&MA Thesis Defense NotificationDownload | G100: 物理系博碩士班學位考試注意事項Physics Department PHD&MA Thesis Defense Noti | H100: https://www.phy.ncu.edu.tw/wp-content/uploads/2026/02/物理系博碩士班學位考試注意事項Physics-Department-PHDMA-Thesis-Defense-Notification-5.pdf | I100: Download | J100: https://www.phy.ncu.edu.tw/wp-content/uploads/2026/02/物理系博碩士班學位考試注意事項Physics-Department-PHDMA-Thesis-Defense-Notification-5.pdf | M100: https://www.phy.ncu.edu.tw/news/114-2-%e7%89%a9%e7%90%86%e7%b3%bb%e5%8d%9a%e7%a2%a9%e5%a3%ab%e7%8f%ad%e5%ad%b8%e4%bd%8d%e8%80%83%e8%a9%a6%e6%b3%a8%e6%84%8f%e4%ba%8b%e9%a0%85physics-department-phdma-thesis-defense-notification/ | N100: 許慧君
A101: =TRUE() | B101: 其他 | D101: 46055 | E101: 114-2物理系研究生申請學分抵免、免修Course Credit Exemption and Waiver | F101: 抵免、免修學分之申請時間：新生（含轉學生）應於入學第一學期或第二學期校曆規定時間內辦理。 New students (including the transfer) should complete the procedure during the appointed period according to the school calendar of the first semester or the second semester. 物理學系碩博士班研究生修業辦法Regulation of Course Requirements for Master and PhD Programs 1050615 時間：2/2-3/6 ———————————————————————————————————————————————————————— 申請法規Regulations： *國立中央大學學分抵免辦法(https://pdc.adm.ncu.edu.tw/rule/rule113/13-0-1.pdf) National Central University Course Credit Waiver Guidelines(https://pdc.adm.ncu.edu.tw/eng/rule/NCU_Doc13_0_ed.pdf) *物理學系碩士班研究生學分抵免辦法Regulation of Credit Transfer – the Master Program *物理學系博士班研究生學分抵免辦法Regulation of Credit Transfer – the Ph.D. Programs ———————————————————————————————————————————————————————— 申請表Application Form： 抵免：國立中央大學學生學分抵免申請表Guidelines for Credits Exemption (抵免成功後，會在成績單上出現該課程，且學分數會加入本學籍） 如果是他校及本校非同系所畢業之研究所新生入學辦理抵免，須多填寫『國立中央大學學生學分抵免申請修讀研究所學分證明』。 免修：物理學系研究生課程免修申請表Application Form for the Waiver of the Courses （免修成功後，表該課程無需再修，但學分數未計入本學籍，亦不會出現在成績單上） 課程抵必修課(限博士生)-物理學系博士生選修外系課程抵PH開頭課程申請表 (如博士班修業辦法註2: 如因研究所需，學生經指導教授同意後，由課程委員會審核通過，可修習本校及台聯大博士班(含碩博同修)課程，以減少上述 PH5、PH6、PH7、PH8、PHT 開頭課程之選修要求。(至多 A 組減少 2 門、B 組減少 2 門、C 組減少 2 門、D 組減少 4 門)。)( With agreement from his/her advisor and the approval of the Department Course Committee, a student taking the PhD courses offered by the University System of Taiwan can reduce the requirement of PH5, PH6, PH7,PH8, and PHT optional courses up to two for Groups A, B, and C and up to four for Group D.) | G101: 物理學系碩博士班研究生修業辦法Regulation of Course Requirements for Master | H101: https://www.phy.ncu.edu.tw/wp-content/uploads/2021/01/%E5%9C%8B%EF%A7%B7%E4%B8%AD%E5%A4%AE%E5%A4%A7%E5%AD%B8%E7%89%A9%EF%A7%A4%E5%AD%B8%E7%B3%BB%E7%A2%A9%E3%80%81%E5%8D%9A%E5%A3%AB%E7%8F%AD%E7%A0%94%E7%A9%B6%E7%94%9F%E4%BF%AE%E6%A5%AD%E8%BE%A6%E6%B3%951050615%E6%95%99%E5%8B%99%E6%9C%83%E8%AD%B0%E9%80%9A%E9%81%8E.pdf | I101: https://pdc.adm.ncu.edu.tw/rule/rule113/13-0-1.pdf | J101: https://pdc.adm.ncu.edu.tw/rule/rule113/13-0-1.pdf | K101: https://pdc.adm.ncu.edu.tw/eng/rule/NCU_Doc13_0_ed.pdf | L101: https://pdc.adm.ncu.edu.tw/eng/rule/NCU_Doc13_0_ed.pdf | M101: https://www.phy.ncu.edu.tw/news/114-2%e7%89%a9%e7%90%86%e7%b3%bb%e7%a0%94%e7%a9%b6%e7%94%9f%e7%94%b3%e8%ab%8b%e5%ad%b8%e5%88%86%e6%8a%b5%e5%85%8d%e3%80%81%e5%85%8d%e4%bf%aecourse-credit-exemption-and-waiver/ | N101: 許慧君
A102: =TRUE() | B102: 其他 | D102: 46052 | E102: 114-2 專題類課程選課調查表-研究生 Questionnaire for Adding Special Topic Courses – for Postgraduate | F102: 研究生如欲選修專題課程，請於115/02/25(三)中午12點前 完成提交調查表：https://forms.gle/FGLEfYSpEfokfEgq6。 Postgraduate students who will take the special topic courses should submit the questionnaire before 12:00 on February 25th (Wednesday). URL:https://forms.gle/FGLEfYSpEfokfEgq6 1. 專題課選課流程：Process of adding special topic courses (1)即日起至115/02/25(三)12點 ：學生填寫本調查表。Students fill out this questionnaire before 12:00 on February 25th (Wednesday). (2)115/02/25(三)下午：系辦公室彙整專題選課名單、送各指導老師確認指導事實及同意修課。The department office sends the student list to each advisor who needs to confirm the instruction fact and agree students to take courses on the afternoon of February 25th (Wednesday). (3)115/03/02(一)：收齊指導教授同意信函後，由系辦公室登入選課系統進行人工加選。 The department office adds courses online for students on March 2nd (Monday). 2.確認專題課是否已加選：Confirm whether the special topic courses have been added 請於 115/03/03(二) 登入選課系統確認所選專題課已加選。若有問題請儘速通知系辦公室。 Please log in to the course selection system on March 3rd (Tues.) to confirm that the selected special topic courses have been added. If you have any problems, please notify the department office as soon as possible. 3.更換專題指導教師請主動通知系辦吳小姐，以免影響學期末成績評分作業。 If you change the advisor during the semester, please notify Ms' Wu of the department office. | G102: https://forms.gle/FGLEfYSpEfokfEgq6 | H102: https://forms.gle/FGLEfYSpEfokfEgq6 | I102: https://forms.gle/FGLEfYSpEfokfEgq6 | J102: https://forms.gle/FGLEfYSpEfokfEgq6 | M102: https://www.phy.ncu.edu.tw/news/114-2-%e5%b0%88%e9%a1%8c%e9%a1%9e%e8%aa%b2%e7%a8%8b%e9%81%b8%e8%aa%b2%e8%aa%bf%e6%9f%a5%e8%a1%a8-%e7%a0%94%e7%a9%b6%e7%94%9f-questionnaire-for-adding-special-topic-courses-for-postgraduate/ | N102: 吳菁穗
...

Sheet 分類統計
A1: 📊 分類統計（公式連動，修改公告總庫資料後自動更新）
A2: 四組統計：八大分類×月份、八大分類×年度、發布者×主分類、發布者×年度。高中生* 為主＋次分類合計，置於總計之外、不重複加總。統計不受「顯示」欄影響。
A3: 分類 | B3: 1月 | C3: 2月 | D3: 3月 | E3: 4月 | F3: 5月 | G3: 6月 | H3: 7月 | I3: 8月 | J3: 9月 | K3: 10月 | L3: 11月 | M3: 12月 | N3: 合計
A4: 招生 | B4: =SUMPRODUCT((公告總庫!$B$9:$B$4019=$A4)*(MONTH(公告總庫!$D$9:$D$4019)=1)) | C4: =SUMPRODUCT((公告總庫!$B$9:$B$4019=$A4)*(MONTH(公告總庫!$D$9:$D$4019)=2)) | D4: =SUMPRODUCT((公告總庫!$B$9:$B$4019=$A4)*(MONTH(公告總庫!$D$9:$D$4019)=3)) | E4: =SUMPRODUCT((公告總庫!$B$9:$B$4019=$A4)*(MONTH(公告總庫!$D$9:$D$4019)=4)) | F4: =SUMPRODUCT((公告總庫!$B$9:$B$4019=$A4)*(MONTH(公告總庫!$D$9:$D$4019)=5)) | G4: =SUMPRODUCT((公告總庫!$B$9:$B$4019=$A4)*(MONTH(公告總庫!$D$9:$D$4019)=6)) | H4: =SUMPRODUCT((公告總庫!$B$9:$B$4019=$A4)*(MONTH(公告總庫!$D$9:$D$4019)=7)) | I4: =SUMPRODUCT((公告總庫!$B$9:$B$4019=$A4)*(MONTH(公告總庫!$D$9:$D$4019)=8)) | J4: =SUMPRODUCT((公告總庫!$B$9:$B$4019=$A4)*(MONTH(公告總庫!$D$9:$D$4019)=9)) | K4: =SUMPRODUCT((公告總庫!$B$9:$B$4019=$A4)*(MONTH(公告總庫!$D$9:$D$4019)=10)) | L4: =SUMPRODUCT((公告總庫!$B$9:$B$4019=$A4)*(MONTH(公告總庫!$D$9:$D$4019)=11)) | M4: =SUMPRODUCT((公告總庫!$B$9:$B$4019=$A4)*(MONTH(公告總庫!$D$9:$D$4019)=12)) | N4: =SUM(B4:M4)
A5: 考試 | B5: =SUMPRODUCT((公告總庫!$B$9:$B$4019=$A5)*(MONTH(公告總庫!$D$9:$D$4019)=1)) | C5: =SUMPRODUCT((公告總庫!$B$9:$B$4019=$A5)*(MONTH(公告總庫!$D$9:$D$4019)=2)) | D5: =SUMPRODUCT((公告總庫!$B$9:$B$4019=$A5)*(MONTH(公告總庫!$D$9:$D$4019)=3)) | E5: =SUMPRODUCT((公告總庫!$B$9:$B$4019=$A5)*(MONTH(公告總庫!$D$9:$D$4019)=4)) | F5: =SUMPRODUCT((公告總庫!$B$9:$B$4019=$A5)*(MONTH(公告總庫!$D$9:$D$4019)=5)) | G5: =SUMPRODUCT((公告總庫!$B$9:$B$4019=$A5)*(MONTH(公告總庫!$D$9:$D$4019)=6)) | H5: =SUMPRODUCT((公告總庫!$B$9:$B$4019=$A5)*(MONTH(公告總庫!$D$9:$D$4019)=7)) | I5: =SUMPRODUCT((公告總庫!$B$9:$B$4019=$A5)*(MONTH(公告總庫!$D$9:$D$4019)=8)) | J5: =SUMPRODUCT((公告總庫!$B$9:$B$4019=$A5)*(MONTH(公告總庫!$D$9:$D$4019)=9)) | K5: =SUMPRODUCT((公告總庫!$B$9:$B$4019=$A5)*(MONTH(公告總庫!$D$9:$D$4019)=10)) | L5: =SUMPRODUCT((公告總庫!$B$9:$B$4019=$A5)*(MONTH(公告總庫!$D$9:$D$4019)=11)) | M5: =SUMPRODUCT((公告總庫!$B$9:$B$4019=$A5)*(MONTH(公告總庫!$D$9:$D$4019)=12)) | N5: =SUM(B5:M5)
A6: 獎學金 | B6: =SUMPRODUCT((公告總庫!$B$9:$B$4019=$A6)*(MONTH(公告總庫!$D$9:$D$4019)=1)) | C6: =SUMPRODUCT((公告總庫!$B$9:$B$4019=$A6)*(MONTH(公告總庫!$D$9:$D$4019)=2)) | D6: =SUMPRODUCT((公告總庫!$B$9:$B$4019=$A6)*(MONTH(公告總庫!$D$9:$D$4019)=3)) | E6: =SUMPRODUCT((公告總庫!$B$9:$B$4019=$A6)*(MONTH(公告總庫!$D$9:$D$4019)=4)) | F6: =SUMPRODUCT((公告總庫!$B$9:$B$4019=$A6)*(MONTH(公告總庫!$D$9:$D$4019)=5)) | G6: =SUMPRODUCT((公告總庫!$B$9:$B$4019=$A6)*(MONTH(公告總庫!$D$9:$D$4019)=6)) | H6: =SUMPRODUCT((公告總庫!$B$9:$B$4019=$A6)*(MONTH(公告總庫!$D$9:$D$4019)=7)) | I6: =SUMPRODUCT((公告總庫!$B$9:$B$4019=$A6)*(MONTH(公告總庫!$D$9:$D$4019)=8)) | J6: =SUMPRODUCT((公告總庫!$B$9:$B$4019=$A6)*(MONTH(公告總庫!$D$9:$D$4019)=9)) | K6: =SUMPRODUCT((公告總庫!$B$9:$B$4019=$A6)*(MONTH(公告總庫!$D$9:$D$4019)=10)) | L6: =SUMPRODUCT((公告總庫!$B$9:$B$4019=$A6)*(MONTH(公告總庫!$D$9:$D$4019)=11)) | M6: =SUMPRODUCT((公告總庫!$B$9:$B$4019=$A6)*(MONTH(公告總庫!$D$9:$D$4019)=12)) | N6: =SUM(B6:M6)
A7: 計畫 | B7: =SUMPRODUCT((公告總庫!$B$9:$B$4019=$A7)*(MONTH(公告總庫!$D$9:$D$4019)=1)) | C7: =SUMPRODUCT((公告總庫!$B$9:$B$4019=$A7)*(MONTH(公告總庫!$D$9:$D$4019)=2)) | D7: =SUMPRODUCT((公告總庫!$B$9:$B$4019=$A7)*(MONTH(公告總庫!$D$9:$D$4019)=3)) | E7: =SUMPRODUCT((公告總庫!$B$9:$B$4019=$A7)*(MONTH(公告總庫!$D$9:$D$4019)=4)) | F7: =SUMPRODUCT((公告總庫!$B$9:$B$4019=$A7)*(MONTH(公告總庫!$D$9:$D$4019)=5)) | G7: =SUMPRODUCT((公告總庫!$B$9:$B$4019=$A7)*(MONTH(公告總庫!$D$9:$D$4019)=6)) | H7: =SUMPRODUCT((公告總庫!$B$9:$B$4019=$A7)*(MONTH(公告總庫!$D$9:$D$4019)=7)) | I7: =SUMPRODUCT((公告總庫!$B$9:$B$4019=$A7)*(MONTH(公告總庫!$D$9:$D$4019)=8)) | J7: =SUMPRODUCT((公告總庫!$B$9:$B$4019=$A7)*(MONTH(公告總庫!$D$9:$D$4019)=9)) | K7: =SUMPRODUCT((公告總庫!$B$9:$B$4019=$A7)*(MONTH(公告總庫!$D$9:$D$4019)=10)) | L7: =SUMPRODUCT((公告總庫!$B$9:$B$4019=$A7)*(MONTH(公告總庫!$D$9:$D$4019)=11)) | M7: =SUMPRODUCT((公告總庫!$B$9:$B$4019=$A7)*(MONTH(公告總庫!$D$9:$D$4019)=12)) | N7: =SUM(B7:M7)
A8: 演講 | B8: =SUMPRODUCT((公告總庫!$B$9:$B$4019=$A8)*(MONTH(公告總庫!$D$9:$D$4019)=1)) | C8: =SUMPRODUCT((公告總庫!$B$9:$B$4019=$A8)*(MONTH(公告總庫!$D$9:$D$4019)=2)) | D8: =SUMPRODUCT((公告總庫!$B$9:$B$4019=$A8)*(MONTH(公告總庫!$D$9:$D$4019)=3)) | E8: =SUMPRODUCT((公告總庫!$B$9:$B$4019=$A8)*(MONTH(公告總庫!$D$9:$D$4019)=4)) | F8: =SUMPRODUCT((公告總庫!$B$9:$B$4019=$A8)*(MONTH(公告總庫!$D$9:$D$4019)=5)) | G8: =SUMPRODUCT((公告總庫!$B$9:$B$4019=$A8)*(MONTH(公告總庫!$D$9:$D$4019)=6)) | H8: =SUMPRODUCT((公告總庫!$B$9:$B$4019=$A8)*(MONTH(公告總庫!$D$9:$D$4019)=7)) | I8: =SUMPRODUCT((公告總庫!$B$9:$B$4019=$A8)*(MONTH(公告總庫!$D$9:$D$4019)=8)) | J8: =SUMPRODUCT((公告總庫!$B$9:$B$4019=$A8)*(MONTH(公告總庫!$D$9:$D$4019)=9)) | K8: =SUMPRODUCT((公告總庫!$B$9:$B$4019=$A8)*(MONTH(公告總庫!$D$9:$D$4019)=10)) | L8: =SUMPRODUCT((公告總庫!$B$9:$B$4019=$A8)*(MONTH(公告總庫!$D$9:$D$4019)=11)) | M8: =SUMPRODUCT((公告總庫!$B$9:$B$4019=$A8)*(MONTH(公告總庫!$D$9:$D$4019)=12)) | N8: =SUM(B8:M8)
A9: 研討會 | B9: =SUMPRODUCT((公告總庫!$B$9:$B$4019=$A9)*(MONTH(公告總庫!$D$9:$D$4019)=1)) | C9: =SUMPRODUCT((公告總庫!$B$9:$B$4019=$A9)*(MONTH(公告總庫!$D$9:$D$4019)=2)) | D9: =SUMPRODUCT((公告總庫!$B$9:$B$4019=$A9)*(MONTH(公告總庫!$D$9:$D$4019)=3)) | E9: =SUMPRODUCT((公告總庫!$B$9:$B$4019=$A9)*(MONTH(公告總庫!$D$9:$D$4019)=4)) | F9: =SUMPRODUCT((公告總庫!$B$9:$B$4019=$A9)*(MONTH(公告總庫!$D$9:$D$4019)=5)) | G9: =SUMPRODUCT((公告總庫!$B$9:$B$4019=$A9)*(MONTH(公告總庫!$D$9:$D$4019)=6)) | H9: =SUMPRODUCT((公告總庫!$B$9:$B$4019=$A9)*(MONTH(公告總庫!$D$9:$D$4019)=7)) | I9: =SUMPRODUCT((公告總庫!$B$9:$B$4019=$A9)*(MONTH(公告總庫!$D$9:$D$4019)=8)) | J9: =SUMPRODUCT((公告總庫!$B$9:$B$4019=$A9)*(MONTH(公告總庫!$D$9:$D$4019)=9)) | K9: =SUMPRODUCT((公告總庫!$B$9:$B$4019=$A9)*(MONTH(公告總庫!$D$9:$D$4019)=10)) | L9: =SUMPRODUCT((公告總庫!$B$9:$B$4019=$A9)*(MONTH(公告總庫!$D$9:$D$4019)=11)) | M9: =SUMPRODUCT((公告總庫!$B$9:$B$4019=$A9)*(MONTH(公告總庫!$D$9:$D$4019)=12)) | N9: =SUM(B9:M9)
A10: 高中生 | B10: =SUMPRODUCT((公告總庫!$B$9:$B$4019=$A10)*(MONTH(公告總庫!$D$9:$D$4019)=1)) | C10: =SUMPRODUCT((公告總庫!$B$9:$B$4019=$A10)*(MONTH(公告總庫!$D$9:$D$4019)=2)) | D10: =SUMPRODUCT((公告總庫!$B$9:$B$4019=$A10)*(MONTH(公告總庫!$D$9:$D$4019)=3)) | E10: =SUMPRODUCT((公告總庫!$B$9:$B$4019=$A10)*(MONTH(公告總庫!$D$9:$D$4019)=4)) | F10: =SUMPRODUCT((公告總庫!$B$9:$B$4019=$A10)*(MONTH(公告總庫!$D$9:$D$4019)=5)) | G10: =SUMPRODUCT((公告總庫!$B$9:$B$4019=$A10)*(MONTH(公告總庫!$D$9:$D$4019)=6)) | H10: =SUMPRODUCT((公告總庫!$B$9:$B$4019=$A10)*(MONTH(公告總庫!$D$9:$D$4019)=7)) | I10: =SUMPRODUCT((公告總庫!$B$9:$B$4019=$A10)*(MONTH(公告總庫!$D$9:$D$4019)=8)) | J10: =SUMPRODUCT((公告總庫!$B$9:$B$4019=$A10)*(MONTH(公告總庫!$D$9:$D$4019)=9)) | K10: =SUMPRODUCT((公告總庫!$B$9:$B$4019=$A10)*(MONTH(公告總庫!$D$9:$D$4019)=10)) | L10: =SUMPRODUCT((公告總庫!$B$9:$B$4019=$A10)*(MONTH(公告總庫!$D$9:$D$4019)=11)) | M10: =SUMPRODUCT((公告總庫!$B$9:$B$4019=$A10)*(MONTH(公告總庫!$D$9:$D$4019)=12)) | N10: =SUM(B10:M10)
A11: 其他 | B11: =SUMPRODUCT((公告總庫!$B$9:$B$4019=$A11)*(MONTH(公告總庫!$D$9:$D$4019)=1)) | C11: =SUMPRODUCT((公告總庫!$B$9:$B$4019=$A11)*(MONTH(公告總庫!$D$9:$D$4019)=2)) | D11: =SUMPRODUCT((公告總庫!$B$9:$B$4019=$A11)*(MONTH(公告總庫!$D$9:$D$4019)=3)) | E11: =SUMPRODUCT((公告總庫!$B$9:$B$4019=$A11)*(MONTH(公告總庫!$D$9:$D$4019)=4)) | F11: =SUMPRODUCT((公告總庫!$B$9:$B$4019=$A11)*(MONTH(公告總庫!$D$9:$D$4019)=5)) | G11: =SUMPRODUCT((公告總庫!$B$9:$B$4019=$A11)*(MONTH(公告總庫!$D$9:$D$4019)=6)) | H11: =SUMPRODUCT((公告總庫!$B$9:$B$4019=$A11)*(MONTH(公告總庫!$D$9:$D$4019)=7)) | I11: =SUMPRODUCT((公告總庫!$B$9:$B$4019=$A11)*(MONTH(公告總庫!$D$9:$D$4019)=8)) | J11: =SUMPRODUCT((公告總庫!$B$9:$B$4019=$A11)*(MONTH(公告總庫!$D$9:$D$4019)=9)) | K11: =SUMPRODUCT((公告總庫!$B$9:$B$4019=$A11)*(MONTH(公告總庫!$D$9:$D$4019)=10)) | L11: =SUMPRODUCT((公告總庫!$B$9:$B$4019=$A11)*(MONTH(公告總庫!$D$9:$D$4019)=11)) | M11: =SUMPRODUCT((公告總庫!$B$9:$B$4019=$A11)*(MONTH(公告總庫!$D$9:$D$4019)=12)) | N11: =SUM(B11:M11)
A12: 總計 | B12: =SUM(B4:B11) | C12: =SUM(C4:C11) | D12: =SUM(D4:D11) | E12: =SUM(E4:E11) | F12: =SUM(F4:F11) | G12: =SUM(G4:G11) | H12: =SUM(H4:H11) | I12: =SUM(I4:I11) | ... N12: =SUM(N4:N11)
A13: 高中生* | B13: =SUMPRODUCT((((公告總庫!$B$9:$B$4019="高中生")+ISNUMBER(FIND("高中生",公告總庫!$C$9:$C$4019)))>0)*(MONTH(公告總庫!$D$9:$D$4019)=1)) | C13: =SUMPRODUCT((((公告總庫!$B$9:$B$4019="高中生")+ISNUMBER(FIND("高中生",公告總庫!$C$9:$C$4019)))>0)*(MONTH(公告總庫!$D$9:$D$4019)=2)) | D13: =SUMPRODUCT((((公告總庫!$B$9:$B$4019="高中生")+ISNUMBER(FIND("高中生",公告總庫!$C$9:$C$4019)))>0)*(MONTH(公告總庫!$D$9:$D$4019)=3)) | E13: =SUMPRODUCT((((公告總庫!$B$9:$B$4019="高中生")+ISNUMBER(FIND("高中生",公告總庫!$C$9:$C$4019)))>0)*(MONTH(公告總庫!$D$9:$D$4019)=4)) | F13: =SUMPRODUCT((((公告總庫!$B$9:$B$4019="高中生")+ISNUMBER(FIND("高中生",公告總庫!$C$9:$C$4019)))>0)*(MONTH(公告總庫!$D$9:$D$4019)=5)) | G13: =SUMPRODUCT((((公告總庫!$B$9:$B$4019="高中生")+ISNUMBER(FIND("高中生",公告總庫!$C$9:$C$4019)))>0)*(MONTH(公告總庫!$D$9:$D$4019)=6)) | H13: =SUMPRODUCT((((公告總庫!$B$9:$B$4019="高中生")+ISNUMBER(FIND("高中生",公告總庫!$C$9:$C$4019)))>0)*(MONTH(公告總庫!$D$9:$D$4019)=7)) | I13: =SUMPRODUCT((((公告總庫!$B$9:$B$4019="高中生")+ISNUMBER(FIND("高中生",公告總庫!$C$9:$C$4019)))>0)*(MONTH(公告總庫!$D$9:$D$4019)=8)) | J13: =SUMPRODUCT((((公告總庫!$B$9:$B$4019="高中生")+ISNUMBER(FIND("高中生",公告總庫!$C$9:$C$4019)))>0)*(MONTH(公告總庫!$D$9:$D$4019)=9)) | K13: =SUMPRODUCT((((公告總庫!$B$9:$B$4019="高中生")+ISNUMBER(FIND("高中生",公告總庫!$C$9:$C$4019)))>0)*(MONTH(公告總庫!$D$9:$D$4019)=10)) | L13: =SUMPRODUCT((((公告總庫!$B$9:$B$4019="高中生")+ISNUMBER(FIND("高中生",公告總庫!$C$9:$C$4019)))>0)*(MONTH(公告總庫!$D$9:$D$4019)=11)) | M13: =SUMPRODUCT((((公告總庫!$B$9:$B$4019="高中生")+ISNUMBER(FIND("高中生",公告總庫!$C$9:$C$4019)))>0)*(MONTH(公告總庫!$D$9:$D$4019)=12)) | N13: =SUM(B13:M13)
A15: 分類 | B15: 2012 | C15: 2013 | D15: 2014 | E15: 2015 | F15: 2016 | G15: 2017 | H15: 2018 | I15: 2019 | J15: 2020 | K15: 2021 | L15: 2022 | M15: 2023 | N15: 2024 | O15: 2025 | P15: 2026 | Q15: 合計
A16: 招生 | B16: =SUMPRODUCT((公告總庫!$B$9:$B$4019=$A16)*(YEAR(公告總庫!$D$9:$D$4019)=2012)) | C16: =SUMPRODUCT((公告總庫!$B$9:$B$4019=$A16)*(YEAR(公告總庫!$D$9:$D$4019)=2013)) | D16: =SUMPRODUCT((公告總庫!$B$9:$B$4019=$A16)*(YEAR(公告總庫!$D$9:$D$4019)=2014)) | E16: =SUMPRODUCT((公告總庫!$B$9:$B$4019=$A16)*(YEAR(公告總庫!$D$9:$D$4019)=2015)) | F16: =SUMPRODUCT((公告總庫!$B$9:$B$4019=$A16)*(YEAR(公告總庫!$D$9:$D$4019)=2016)) | G16: =SUMPRODUCT((公告總庫!$B$9:$B$4019=$A16)*(YEAR(公告總庫!$D$9:$D$4019)=2017)) | H16: =SUMPRODUCT((公告總庫!$B$9:$B$4019=$A16)*(YEAR(公告總庫!$D$9:$D$4019)=2018)) | I16: =SUMPRODUCT((公告總庫!$B$9:$B$4019=$A16)*(YEAR(公告總庫!$D$9:$D$4019)=2019)) | J16: =SUMPRODUCT((公告總庫!$B$9:$B$4019=$A16)*(YEAR(公告總庫!$D$9:$D$4019)=2020)) | K16: =SUMPRODUCT((公告總庫!$B$9:$B$4019=$A16)*(YEAR(公告總庫!$D$9:$D$4019)=2021)) | L16: =SUMPRODUCT((公告總庫!$B$9:$B$4019=$A16)*(YEAR(公告總庫!$D$9:$D$4019)=2022)) | M16: =SUMPRODUCT((公告總庫!$B$9:$B$4019=$A16)*(YEAR(公告總庫!$D$9:$D$4019)=2023)) | N16: =SUMPRODUCT((公告總庫!$B$9:$B$4019=$A16)*(YEAR(公告總庫!$D$9:$D$4019)=2024)) | O16: =SUMPRODUCT((公告總庫!$B$9:$B$4019=$A16)*(YEAR(公告總庫!$D$9:$D$4019)=2025)) | P16: =SUMPRODUCT((公告總庫!$B$9:$B$4019=$A16)*(YEAR(公告總庫!$D$9:$D$4019)=2026)) | Q16: =SUM(B16:P16)
A17: 考試 | B17: =SUMPRODUCT((公告總庫!$B$9:$B$4019=$A17)*(YEAR(公告總庫!$D$9:$D$4019)=2012)) | C17: =SUMPRODUCT((公告總庫!$B$9:$B$4019=$A17)*(YEAR(公告總庫!$D$9:$D$4019)=2013)) | D17: =SUMPRODUCT((公告總庫!$B$9:$B$4019=$A17)*(YEAR(公告總庫!$D$9:$D$4019)=2014)) | E17: =SUMPRODUCT((公告總庫!$B$9:$B$4019=$A17)*(YEAR(公告總庫!$D$9:$D$4019)=2015)) | F17: =SUMPRODUCT((公告總庫!$B$9:$B$4019=$A17)*(YEAR(公告總庫!$D$9:$D$4019)=2016)) | G17: =SUMPRODUCT((公告總庫!$B$9:$B$4019=$A17)*(YEAR(公告總庫!$D$9:$D$4019)=2017)) | H17: =SUMPRODUCT((公告總庫!$B$9:$B$4019=$A17)*(YEAR(公告總庫!$D$9:$D$4019)=2018)) | I17: =SUMPRODUCT((公告總庫!$B$9:$B$4019=$A17)*(YEAR(公告總庫!$D$9:$D$4019)=2019)) | J17: =SUMPRODUCT((公告總庫!$B$9:$B$4019=$A17)*(YEAR(公告總庫!$D$9:$D$4019)=2020)) | K17: =SUMPRODUCT((公告總庫!$B$9:$B$4019=$A17)*(YEAR(公告總庫!$D$9:$D$4019)=2021)) | L17: =SUMPRODUCT((公告總庫!$B$9:$B$4019=$A17)*(YEAR(公告總庫!$D$9:$D$4019)=2022)) | M17: =SUMPRODUCT((公告總庫!$B$9:$B$4019=$A17)*(YEAR(公告總庫!$D$9:$D$4019)=2023)) | N17: =SUMPRODUCT((公告總庫!$B$9:$B$4019=$A17)*(YEAR(公告總庫!$D$9:$D$4019)=2024)) | O17: =SUMPRODUCT((公告總庫!$B$9:$B$4019=$A17)*(YEAR(公告總庫!$D$9:$D$4019)=2025)) | P17: =SUMPRODUCT((公告總庫!$B$9:$B$4019=$A17)*(YEAR(公告總庫!$D$9:$D$4019)=2026)) | Q17: =SUM(B17:P17)
A18: 獎學金 | B18: =SUMPRODUCT((公告總庫!$B$9:$B$4019=$A18)*(YEAR(公告總庫!$D$9:$D$4019)=2012)) | C18: =SUMPRODUCT((公告總庫!$B$9:$B$4019=$A18)*(YEAR(公告總庫!$D$9:$D$4019)=2013)) | D18: =SUMPRODUCT((公告總庫!$B$9:$B$4019=$A18)*(YEAR(公告總庫!$D$9:$D$4019)=2014)) | E18: =SUMPRODUCT((公告總庫!$B$9:$B$4019=$A18)*(YEAR(公告總庫!$D$9:$D$4019)=2015)) | F18: =SUMPRODUCT((公告總庫!$B$9:$B$4019=$A18)*(YEAR(公告總庫!$D$9:$D$4019)=2016)) | G18: =SUMPRODUCT((公告總庫!$B$9:$B$4019=$A18)*(YEAR(公告總庫!$D$9:$D$4019)=2017)) | H18: =SUMPRODUCT((公告總庫!$B$9:$B$4019=$A18)*(YEAR(公告總庫!$D$9:$D$4019)=2018)) | I18: =SUMPRODUCT((公告總庫!$B$9:$B$4019=$A18)*(YEAR(公告總庫!$D$9:$D$4019)=2019)) | J18: =SUMPRODUCT((公告總庫!$B$9:$B$4019=$A18)*(YEAR(公告總庫!$D$9:$D$4019)=2020)) | K18: =SUMPRODUCT((公告總庫!$B$9:$B$4019=$A18)*(YEAR(公告總庫!$D$9:$D$4019)=2021)) | L18: =SUMPRODUCT((公告總庫!$B$9:$B$4019=$A18)*(YEAR(公告總庫!$D$9:$D$4019)=2022)) | M18: =SUMPRODUCT((公告總庫!$B$9:$B$4019=$A18)*(YEAR(公告總庫!$D$9:$D$4019)=2023)) | N18: =SUMPRODUCT((公告總庫!$B$9:$B$4019=$A18)*(YEAR(公告總庫!$D$9:$D$4019)=2024)) | O18: =SUMPRODUCT((公告總庫!$B$9:$B$4019=$A18)*(YEAR(公告總庫!$D$9:$D$4019)=2025)) | P18: =SUMPRODUCT((公告總庫!$B$9:$B$4019=$A18)*(YEAR(公告總庫!$D$9:$D$4019)=2026)) | Q18: =SUM(B18:P18)
A19: 計畫 | B19: =SUMPRODUCT((公告總庫!$B$9:$B$4019=$A19)*(YEAR(公告總庫!$D$9:$D$4019)=2012)) | C19: =SUMPRODUCT((公告總庫!$B$9:$B$4019=$A19)*(YEAR(公告總庫!$D$9:$D$4019)=2013)) | D19: =SUMPRODUCT((公告總庫!$B$9:$B$4019=$A19)*(YEAR(公告總庫!$D$9:$D$4019)=2014)) | E19: =SUMPRODUCT((公告總庫!$B$9:$B$4019=$A19)*(YEAR(公告總庫!$D$9:$D$4019)=2015)) | F19: =SUMPRODUCT((公告總庫!$B$9:$B$4019=$A19)*(YEAR(公告總庫!$D$9:$D$4019)=2016)) | G19: =SUMPRODUCT((公告總庫!$B$9:$B$4019=$A19)*(YEAR(公告總庫!$D$9:$D$4019)=2017)) | H19: =SUMPRODUCT((公告總庫!$B$9:$B$4019=$A19)*(YEAR(公告總庫!$D$9:$D$4019)=2018)) | I19: =SUMPRODUCT((公告總庫!$B$9:$B$4019=$A19)*(YEAR(公告總庫!$D$9:$D$4019)=2019)) | J19: =SUMPRODUCT((公告總庫!$B$9:$B$4019=$A19)*(YEAR(公告總庫!$D$9:$D$4019)=2020)) | K19: =SUMPRODUCT((公告總庫!$B$9:$B$4019=$A19)*(YEAR(公告總庫!$D$9:$D$4019)=2021)) | L19: =SUMPRODUCT((公告總庫!$B$9:$B$4019=$A19)*(YEAR(公告總庫!$D$9:$D$4019)=2022)) | M19: =SUMPRODUCT((公告總庫!$B$9:$B$4019=$A19)*(YEAR(公告總庫!$D$9:$D$4019)=2023)) | N19: =SUMPRODUCT((公告總庫!$B$9:$B$4019=$A19)*(YEAR(公告總庫!$D$9:$D$4019)=2024)) | O19: =SUMPRODUCT((公告總庫!$B$9:$B$4019=$A19)*(YEAR(公告總庫!$D$9:$D$4019)=2025)) | P19: =SUMPRODUCT((公告總庫!$B$9:$B$4019=$A19)*(YEAR(公告總庫!$D$9:$D$4019)=2026)) | Q19: =SUM(B19:P19)
A20: 演講 | B20: =SUMPRODUCT((公告總庫!$B$9:$B$4019=$A20)*(YEAR(公告總庫!$D$9:$D$4019)=2012)) | C20: =SUMPRODUCT((公告總庫!$B$9:$B$4019=$A20)*(YEAR(公告總庫!$D$9:$D$4019)=2013)) | D20: =SUMPRODUCT((公告總庫!$B$9:$B$4019=$A20)*(YEAR(公告總庫!$D$9:$D$4019)=2014)) | E20: =SUMPRODUCT((公告總庫!$B$9:$B$4019=$A20)*(YEAR(公告總庫!$D$9:$D$4019)=2015)) | F20: =SUMPRODUCT((公告總庫!$B$9:$B$4019=$A20)*(YEAR(公告總庫!$D$9:$D$4019)=2016)) | G20: =SUMPRODUCT((公告總庫!$B$9:$B$4019=$A20)*(YEAR(公告總庫!$D$9:$D$4019)=2017)) | H20: =SUMPRODUCT((公告總庫!$B$9:$B$4019=$A20)*(YEAR(公告總庫!$D$9:$D$4019)=2018)) | I20: =SUMPRODUCT((公告總庫!$B$9:$B$4019=$A20)*(YEAR(公告總庫!$D$9:$D$4019)=2019)) | J20: =SUMPRODUCT((公告總庫!$B$9:$B$4019=$A20)*(YEAR(公告總庫!$D$9:$D$4019)=2020)) | K20: =SUMPRODUCT((公告總庫!$B$9:$B$4019=$A20)*(YEAR(公告總庫!$D$9:$D$4019)=2021)) | L20: =SUMPRODUCT((公告總庫!$B$9:$B$4019=$A20)*(YEAR(公告總庫!$D$9:$D$4019)=2022)) | M20: =SUMPRODUCT((公告總庫!$B$9:$B$4019=$A20)*(YEAR(公告總庫!$D$9:$D$4019)=2023)) | N20: =SUMPRODUCT((公告總庫!$B$9:$B$4019=$A20)*(YEAR(公告總庫!$D$9:$D$4019)=2024)) | O20: =SUMPRODUCT((公告總庫!$B$9:$B$4019=$A20)*(YEAR(公告總庫!$D$9:$D$4019)=2025)) | P20: =SUMPRODUCT((公告總庫!$B$9:$B$4019=$A20)*(YEAR(公告總庫!$D$9:$D$4019)=2026)) | Q20: =SUM(B20:P20)
A21: 研討會 | B21: =SUMPRODUCT((公告總庫!$B$9:$B$4019=$A21)*(YEAR(公告總庫!$D$9:$D$4019)=2012)) | C21: =SUMPRODUCT((公告總庫!$B$9:$B$4019=$A21)*(YEAR(公告總庫!$D$9:$D$4019)=2013)) | D21: =SUMPRODUCT((公告總庫!$B$9:$B$4019=$A21)*(YEAR(公告總庫!$D$9:$D$4019)=2014)) | E21: =SUMPRODUCT((公告總庫!$B$9:$B$4019=$A21)*(YEAR(公告總庫!$D$9:$D$4019)=2015)) | F21: =SUMPRODUCT((公告總庫!$B$9:$B$4019=$A21)*(YEAR(公告總庫!$D$9:$D$4019)=2016)) | G21: =SUMPRODUCT((公告總庫!$B$9:$B$4019=$A21)*(YEAR(公告總庫!$D$9:$D$4019)=2017)) | H21: =SUMPRODUCT((公告總庫!$B$9:$B$4019=$A21)*(YEAR(公告總庫!$D$9:$D$4019)=2018)) | I21: =SUMPRODUCT((公告總庫!$B$9:$B$4019=$A21)*(YEAR(公告總庫!$D$9:$D$4019)=2019)) | J21: =SUMPRODUCT((公告總庫!$B$9:$B$4019=$A21)*(YEAR(公告總庫!$D$9:$D$4019)=2020)) | K21: =SUMPRODUCT((公告總庫!$B$9:$B$4019=$A21)*(YEAR(公告總庫!$D$9:$D$4019)=2021)) | L21: =SUMPRODUCT((公告總庫!$B$9:$B$4019=$A21)*(YEAR(公告總庫!$D$9:$D$4019)=2022)) | M21: =SUMPRODUCT((公告總庫!$B$9:$B$4019=$A21)*(YEAR(公告總庫!$D$9:$D$4019)=2023)) | N21: =SUMPRODUCT((公告總庫!$B$9:$B$4019=$A21)*(YEAR(公告總庫!$D$9:$D$4019)=2024)) | O21: =SUMPRODUCT((公告總庫!$B$9:$B$4019=$A21)*(YEAR(公告總庫!$D$9:$D$4019)=2025)) | P21: =SUMPRODUCT((公告總庫!$B$9:$B$4019=$A21)*(YEAR(公告總庫!$D$9:$D$4019)=2026)) | Q21: =SUM(B21:P21)
A22: 高中生 | B22: =SUMPRODUCT((公告總庫!$B$9:$B$4019=$A22)*(YEAR(公告總庫!$D$9:$D$4019)=2012)) | C22: =SUMPRODUCT((公告總庫!$B$9:$B$4019=$A22)*(YEAR(公告總庫!$D$9:$D$4019)=2013)) | D22: =SUMPRODUCT((公告總庫!$B$9:$B$4019=$A22)*(YEAR(公告總庫!$D$9:$D$4019)=2014)) | E22: =SUMPRODUCT((公告總庫!$B$9:$B$4019=$A22)*(YEAR(公告總庫!$D$9:$D$4019)=2015)) | F22: =SUMPRODUCT((公告總庫!$B$9:$B$4019=$A22)*(YEAR(公告總庫!$D$9:$D$4019)=2016)) | G22: =SUMPRODUCT((公告總庫!$B$9:$B$4019=$A22)*(YEAR(公告總庫!$D$9:$D$4019)=2017)) | H22: =SUMPRODUCT((公告總庫!$B$9:$B$4019=$A22)*(YEAR(公告總庫!$D$9:$D$4019)=2018)) | I22: =SUMPRODUCT((公告總庫!$B$9:$B$4019=$A22)*(YEAR(公告總庫!$D$9:$D$4019)=2019)) | J22: =SUMPRODUCT((公告總庫!$B$9:$B$4019=$A22)*(YEAR(公告總庫!$D$9:$D$4019)=2020)) | K22: =SUMPRODUCT((公告總庫!$B$9:$B$4019=$A22)*(YEAR(公告總庫!$D$9:$D$4019)=2021)) | L22: =SUMPRODUCT((公告總庫!$B$9:$B$4019=$A22)*(YEAR(公告總庫!$D$9:$D$4019)=2022)) | M22: =SUMPRODUCT((公告總庫!$B$9:$B$4019=$A22)*(YEAR(公告總庫!$D$9:$D$4019)=2023)) | N22: =SUMPRODUCT((公告總庫!$B$9:$B$4019=$A22)*(YEAR(公告總庫!$D$9:$D$4019)=2024)) | O22: =SUMPRODUCT((公告總庫!$B$9:$B$4019=$A22)*(YEAR(公告總庫!$D$9:$D$4019)=2025)) | P22: =SUMPRODUCT((公告總庫!$B$9:$B$4019=$A22)*(YEAR(公告總庫!$D$9:$D$4019)=2026)) | Q22: =SUM(B22:P22)
A23: 其他 | B23: =SUMPRODUCT((公告總庫!$B$9:$B$4019=$A23)*(YEAR(公告總庫!$D$9:$D$4019)=2012)) | C23: =SUMPRODUCT((公告總庫!$B$9:$B$4019=$A23)*(YEAR(公告總庫!$D$9:$D$4019)=2013)) | D23: =SUMPRODUCT((公告總庫!$B$9:$B$4019=$A23)*(YEAR(公告總庫!$D$9:$D$4019)=2014)) | E23: =SUMPRODUCT((公告總庫!$B$9:$B$4019=$A23)*(YEAR(公告總庫!$D$9:$D$4019)=2015)) | F23: =SUMPRODUCT((公告總庫!$B$9:$B$4019=$A23)*(YEAR(公告總庫!$D$9:$D$4019)=2016)) | G23: =SUMPRODUCT((公告總庫!$B$9:$B$4019=$A23)*(YEAR(公告總庫!$D$9:$D$4019)=2017)) | H23: =SUMPRODUCT((公告總庫!$B$9:$B$4019=$A23)*(YEAR(公告總庫!$D$9:$D$4019)=2018)) | I23: =SUMPRODUCT((公告總庫!$B$9:$B$4019=$A23)*(YEAR(公告總庫!$D$9:$D$4019)=2019)) | J23: =SUMPRODUCT((公告總庫!$B$9:$B$4019=$A23)*(YEAR(公告總庫!$D$9:$D$4019)=2020)) | K23: =SUMPRODUCT((公告總庫!$B$9:$B$4019=$A23)*(YEAR(公告總庫!$D$9:$D$4019)=2021)) | L23: =SUMPRODUCT((公告總庫!$B$9:$B$4019=$A23)*(YEAR(公告總庫!$D$9:$D$4019)=2022)) | M23: =SUMPRODUCT((公告總庫!$B$9:$B$4019=$A23)*(YEAR(公告總庫!$D$9:$D$4019)=2023)) | N23: =SUMPRODUCT((公告總庫!$B$9:$B$4019=$A23)*(YEAR(公告總庫!$D$9:$D$4019)=2024)) | O23: =SUMPRODUCT((公告總庫!$B$9:$B$4019=$A23)*(YEAR(公告總庫!$D$9:$D$4019)=2025)) | P23: =SUMPRODUCT((公告總庫!$B$9:$B$4019=$A23)*(YEAR(公告總庫!$D$9:$D$4019)=2026)) | Q23: =SUM(B23:P23)
A24: 總計 | B24: =SUM(B16:B23) | C24: =SUM(C16:C23) | D24: =SUM(D16:D23) | E24: =SUM(E16:E23) | F24: =SUM(F16:F23) | G24: =SUM(G16:G23) | H24: =SUM(H16:H23) | I24: =SUM(I16:I23) | ... Q24: =SUM(Q16:Q23)
A25: 高中生* | B25: =SUMPRODUCT((((公告總庫!$B$9:$B$4019="高中生")+ISNUMBER(FIND("高中生",公告總庫!$C$9:$C$4019)))>0)*(YEAR(公告總庫!$D$9:$D$4019)=2012)) | C25: =SUMPRODUCT((((公告總庫!$B$9:$B$4019="高中生")+ISNUMBER(FIND("高中生",公告總庫!$C$9:$C$4019)))>0)*(YEAR(公告總庫!$D$9:$D$4019)=2013)) | D25: =SUMPRODUCT((((公告總庫!$B$9:$B$4019="高中生")+ISNUMBER(FIND("高中生",公告總庫!$C$9:$C$4019)))>0)*(YEAR(公告總庫!$D$9:$D$4019)=2014)) | E25: =SUMPRODUCT((((公告總庫!$B$9:$B$4019="高中生")+ISNUMBER(FIND("高中生",公告總庫!$C$9:$C$4019)))>0)*(YEAR(公告總庫!$D$9:$D$4019)=2015)) | F25: =SUMPRODUCT((((公告總庫!$B$9:$B$4019="高中生")+ISNUMBER(FIND("高中生",公告總庫!$C$9:$C$4019)))>0)*(YEAR(公告總庫!$D$9:$D$4019)=2016)) | G25: =SUMPRODUCT((((公告總庫!$B$9:$B$4019="高中生")+ISNUMBER(FIND("高中生",公告總庫!$C$9:$C$4019)))>0)*(YEAR(公告總庫!$D$9:$D$4019)=2017)) | H25: =SUMPRODUCT((((公告總庫!$B$9:$B$4019="高中生")+ISNUMBER(FIND("高中生",公告總庫!$C$9:$C$4019)))>0)*(YEAR(公告總庫!$D$9:$D$4019)=2018)) | I25: =SUMPRODUCT((((公告總庫!$B$9:$B$4019="高中生")+ISNUMBER(FIND("高中生",公告總庫!$C$9:$C$4019)))>0)*(YEAR(公告總庫!$D$9:$D$4019)=2019)) | J25: =SUMPRODUCT((((公告總庫!$B$9:$B$4019="高中生")+ISNUMBER(FIND("高中生",公告總庫!$C$9:$C$4019)))>0)*(YEAR(公告總庫!$D$9:$D$4019)=2020)) | K25: =SUMPRODUCT((((公告總庫!$B$9:$B$4019="高中生")+ISNUMBER(FIND("高中生",公告總庫!$C$9:$C$4019)))>0)*(YEAR(公告總庫!$D$9:$D$4019)=2021)) | L25: =SUMPRODUCT((((公告總庫!$B$9:$B$4019="高中生")+ISNUMBER(FIND("高中生",公告總庫!$C$9:$C$4019)))>0)*(YEAR(公告總庫!$D$9:$D$4019)=2022)) | M25: =SUMPRODUCT((((公告總庫!$B$9:$B$4019="高中生")+ISNUMBER(FIND("高中生",公告總庫!$C$9:$C$4019)))>0)*(YEAR(公告總庫!$D$9:$D$4019)=2023)) | N25: =SUMPRODUCT((((公告總庫!$B$9:$B$4019="高中生")+ISNUMBER(FIND("高中生",公告總庫!$C$9:$C$4019)))>0)*(YEAR(公告總庫!$D$9:$D$4019)=2024)) | O25: =SUMPRODUCT((((公告總庫!$B$9:$B$4019="高中生")+ISNUMBER(FIND("高中生",公告總庫!$C$9:$C$4019)))>0)*(YEAR(公告總庫!$D$9:$D$4019)=2025)) | P25: =SUMPRODUCT((((公告總庫!$B$9:$B$4019="高中生")+ISNUMBER(FIND("高中生",公告總庫!$C$9:$C$4019)))>0)*(YEAR(公告總庫!$D$9:$D$4019)=2026)) | Q25: =SUM(B25:P25)
A27: 發布者 | B27: 招生 | C27: 考試 | D27: 獎學金 | E27: 計畫 | F27: 演講 | G27: 研討會 | H27: 高中生 | I27: 其他 | J27: 合計
A28: 許慧君 | B28: =SUMPRODUCT((公告總庫!$N$9:$N$4019=$A28)*(公告總庫!$B$9:$B$4019="招生")) | C28: =SUMPRODUCT((公告總庫!$N$9:$N$4019=$A28)*(公告總庫!$B$9:$B$4019="考試")) | D28: =SUMPRODUCT((公告總庫!$N$9:$N$4019=$A28)*(公告總庫!$B$9:$B$4019="獎學金")) | E28: =SUMPRODUCT((公告總庫!$N$9:$N$4019=$A28)*(公告總庫!$B$9:$B$4019="計畫")) | F28: =SUMPRODUCT((公告總庫!$N$9:$N$4019=$A28)*(公告總庫!$B$9:$B$4019="演講")) | G28: =SUMPRODUCT((公告總庫!$N$9:$N$4019=$A28)*(公告總庫!$B$9:$B$4019="研討會")) | H28: =SUMPRODUCT((公告總庫!$N$9:$N$4019=$A28)*(公告總庫!$B$9:$B$4019="高中生")) | I28: =SUMPRODUCT((公告總庫!$N$9:$N$4019=$A28)*(公告總庫!$B$9:$B$4019="其他")) | J28: =SUM(B28:I28)
A29: 劉怡貞 | B29: =SUMPRODUCT((公告總庫!$N$9:$N$4019=$A29)*(公告總庫!$B$9:$B$4019="招生")) | C29: =SUMPRODUCT((公告總庫!$N$9:$N$4019=$A29)*(公告總庫!$B$9:$B$4019="考試")) | D29: =SUMPRODUCT((公告總庫!$N$9:$N$4019=$A29)*(公告總庫!$B$9:$B$4019="獎學金")) | E29: =SUMPRODUCT((公告總庫!$N$9:$N$4019=$A29)*(公告總庫!$B$9:$B$4019="計畫")) | F29: =SUMPRODUCT((公告總庫!$N$9:$N$4019=$A29)*(公告總庫!$B$9:$B$4019="演講")) | G29: =SUMPRODUCT((公告總庫!$N$9:$N$4019=$A29)*(公告總庫!$B$9:$B$4019="研討會")) | H29: =SUMPRODUCT((公告總庫!$N$9:$N$4019=$A29)*(公告總庫!$B$9:$B$4019="高中生")) | I29: =SUMPRODUCT((公告總庫!$N$9:$N$4019=$A29)*(公告總庫!$B$9:$B$4019="其他")) | J29: =SUM(B29:I29)
A30: 吳菁穗 | B30: =SUMPRODUCT((公告總庫!$N$9:$N$4019=$A30)*(公告總庫!$B$9:$B$4019="招生")) | C30: =SUMPRODUCT((公告總庫!$N$9:$N$4019=$A30)*(公告總庫!$B$9:$B$4019="考試")) | D30: =SUMPRODUCT((公告總庫!$N$9:$N$4019=$A30)*(公告總庫!$B$9:$B$4019="獎學金")) | E30: =SUMPRODUCT((公告總庫!$N$9:$N$4019=$A30)*(公告總庫!$B$9:$B$4019="計畫")) | F30: =SUMPRODUCT((公告總庫!$N$9:$N$4019=$A30)*(公告總庫!$B$9:$B$4019="演講")) | G30: =SUMPRODUCT((公告總庫!$N$9:$N$4019=$A30)*(公告總庫!$B$9:$B$4019="研討會")) | H30: =SUMPRODUCT((公告總庫!$N$9:$N$4019=$A30)*(公告總庫!$B$9:$B$4019="高中生")) | I30: =SUMPRODUCT((公告總庫!$N$9:$N$4019=$A30)*(公告總庫!$B$9:$B$4019="其他")) | J30: =SUM(B30:I30)
A31: 黃寶輝 | B31: =SUMPRODUCT((公告總庫!$N$9:$N$4019=$A31)*(公告總庫!$B$9:$B$4019="招生")) | C31: =SUMPRODUCT((公告總庫!$N$9:$N$4019=$A31)*(公告總庫!$B$9:$B$4019="考試")) | D31: =SUMPRODUCT((公告總庫!$N$9:$N$4019=$A31)*(公告總庫!$B$9:$B$4019="獎學金")) | E31: =SUMPRODUCT((公告總庫!$N$9:$N$4019=$A31)*(公告總庫!$B$9:$B$4019="計畫")) | F31: =SUMPRODUCT((公告總庫!$N$9:$N$4019=$A31)*(公告總庫!$B$9:$B$4019="演講")) | G31: =SUMPRODUCT((公告總庫!$N$9:$N$4019=$A31)*(公告總庫!$B$9:$B$4019="研討會")) | H31: =SUMPRODUCT((公告總庫!$N$9:$N$4019=$A31)*(公告總庫!$B$9:$B$4019="高中生")) | I31: =SUMPRODUCT((公告總庫!$N$9:$N$4019=$A31)*(公告總庫!$B$9:$B$4019="其他")) | J31: =SUM(B31:I31)
A32: 其他帳號 | B32: =SUMPRODUCT((公告總庫!$B$9:$B$4019="招生")*1)-SUM(B28:B31) | C32: =SUMPRODUCT((公告總庫!$B$9:$B$4019="考試")*1)-SUM(C28:C31) | D32: =SUMPRODUCT((公告總庫!$B$9:$B$4019="獎學金")*1)-SUM(D28:D31) | E32: =SUMPRODUCT((公告總庫!$B$9:$B$4019="計畫")*1)-SUM(E28:E31) | F32: =SUMPRODUCT((公告總庫!$B$9:$B$4019="演講")*1)-SUM(F28:F31) | G32: =SUMPRODUCT((公告總庫!$B$9:$B$4019="研討會")*1)-SUM(G28:G31) | H32: =SUMPRODUCT((公告總庫!$B$9:$B$4019="高中生")*1)-SUM(H28:H31) | I32: =SUMPRODUCT((公告總庫!$B$9:$B$4019="其他")*1)-SUM(I28:I31) | J32: =SUM(B32:I32)
A33: 總計 | B33: =SUM(B28:B32) | C33: =SUM(C28:C32) | D33: =SUM(D28:D32) | E33: =SUM(E28:E32) | F33: =SUM(F28:F32) | G33: =SUM(G28:G32) | H33: =SUM(H28:H32) | I33: =SUM(I28:I32) | J33: =SUM(J28:J32)
A35: 發布者 | B35: 2012 | C35: 2013 | D35: 2014 | E35: 2015 | F35: 2016 | G35: 2017 | H35: 2018 | I35: 2019 | J35: 2020 | K35: 2021 | L35: 2022 | M35: 2023 | N35: 2024 | O35: 2025 | P35: 2026 | Q35: 合計
A36: 許慧君 | B36: =SUMPRODUCT((公告總庫!$N$9:$N$4019=$A36)*(YEAR(公告總庫!$D$9:$D$4019)=2012)) | C36: =SUMPRODUCT((公告總庫!$N$9:$N$4019=$A36)*(YEAR(公告總庫!$D$9:$D$4019)=2013)) | D36: =SUMPRODUCT((公告總庫!$N$9:$N$4019=$A36)*(YEAR(公告總庫!$D$9:$D$4019)=2014)) | E36: =SUMPRODUCT((公告總庫!$N$9:$N$4019=$A36)*(YEAR(公告總庫!$D$9:$D$4019)=2015)) | F36: =SUMPRODUCT((公告總庫!$N$9:$N$4019=$A36)*(YEAR(公告總庫!$D$9:$D$4019)=2016)) | G36: =SUMPRODUCT((公告總庫!$N$9:$N$4019=$A36)*(YEAR(公告總庫!$D$9:$D$4019)=2017)) | H36: =SUMPRODUCT((公告總庫!$N$9:$N$4019=$A36)*(YEAR(公告總庫!$D$9:$D$4019)=2018)) | I36: =SUMPRODUCT((公告總庫!$N$9:$N$4019=$A36)*(YEAR(公告總庫!$D$9:$D$4019)=2019)) | J36: =SUMPRODUCT((公告總庫!$N$9:$N$4019=$A36)*(YEAR(公告總庫!$D$9:$D$4019)=2020)) | K36: =SUMPRODUCT((公告總庫!$N$9:$N$4019=$A36)*(YEAR(公告總庫!$D$9:$D$4019)=2021)) | L36: =SUMPRODUCT((公告總庫!$N$9:$N$4019=$A36)*(YEAR(公告總庫!$D$9:$D$4019)=2022)) | M36: =SUMPRODUCT((公告總庫!$N$9:$N$4019=$A36)*(YEAR(公告總庫!$D$9:$D$4019)=2023)) | N36: =SUMPRODUCT((公告總庫!$N$9:$N$4019=$A36)*(YEAR(公告總庫!$D$9:$D$4019)=2024)) | O36: =SUMPRODUCT((公告總庫!$N$9:$N$4019=$A36)*(YEAR(公告總庫!$D$9:$D$4019)=2025)) | P36: =SUMPRODUCT((公告總庫!$N$9:$N$4019=$A36)*(YEAR(公告總庫!$D$9:$D$4019)=2026)) | Q36: =SUM(B36:P36)
A37: 劉怡貞 | B37: =SUMPRODUCT((公告總庫!$N$9:$N$4019=$A37)*(YEAR(公告總庫!$D$9:$D$4019)=2012)) | C37: =SUMPRODUCT((公告總庫!$N$9:$N$4019=$A37)*(YEAR(公告總庫!$D$9:$D$4019)=2013)) | D37: =SUMPRODUCT((公告總庫!$N$9:$N$4019=$A37)*(YEAR(公告總庫!$D$9:$D$4019)=2014)) | E37: =SUMPRODUCT((公告總庫!$N$9:$N$4019=$A37)*(YEAR(公告總庫!$D$9:$D$4019)=2015)) | F37: =SUMPRODUCT((公告總庫!$N$9:$N$4019=$A37)*(YEAR(公告總庫!$D$9:$D$4019)=2016)) | G37: =SUMPRODUCT((公告總庫!$N$9:$N$4019=$A37)*(YEAR(公告總庫!$D$9:$D$4019)=2017)) | H37: =SUMPRODUCT((公告總庫!$N$9:$N$4019=$A37)*(YEAR(公告總庫!$D$9:$D$4019)=2018)) | I37: =SUMPRODUCT((公告總庫!$N$9:$N$4019=$A37)*(YEAR(公告總庫!$D$9:$D$4019)=2019)) | J37: =SUMPRODUCT((公告總庫!$N$9:$N$4019=$A37)*(YEAR(公告總庫!$D$9:$D$4019)=2020)) | K37: =SUMPRODUCT((公告總庫!$N$9:$N$4019=$A37)*(YEAR(公告總庫!$D$9:$D$4019)=2021)) | L37: =SUMPRODUCT((公告總庫!$N$9:$N$4019=$A37)*(YEAR(公告總庫!$D$9:$D$4019)=2022)) | M37: =SUMPRODUCT((公告總庫!$N$9:$N$4019=$A37)*(YEAR(公告總庫!$D$9:$D$4019)=2023)) | N37: =SUMPRODUCT((公告總庫!$N$9:$N$4019=$A37)*(YEAR(公告總庫!$D$9:$D$4019)=2024)) | O37: =SUMPRODUCT((公告總庫!$N$9:$N$4019=$A37)*(YEAR(公告總庫!$D$9:$D$4019)=2025)) | P37: =SUMPRODUCT((公告總庫!$N$9:$N$4019=$A37)*(YEAR(公告總庫!$D$9:$D$4019)=2026)) | Q37: =SUM(B37:P37)
A38: 吳菁穗 | B38: =SUMPRODUCT((公告總庫!$N$9:$N$4019=$A38)*(YEAR(公告總庫!$D$9:$D$4019)=2012)) | C38: =SUMPRODUCT((公告總庫!$N$9:$N$4019=$A38)*(YEAR(公告總庫!$D$9:$D$4019)=2013)) | D38: =SUMPRODUCT((公告總庫!$N$9:$N$4019=$A38)*(YEAR(公告總庫!$D$9:$D$4019)=2014)) | E38: =SUMPRODUCT((公告總庫!$N$9:$N$4019=$A38)*(YEAR(公告總庫!$D$9:$D$4019)=2015)) | F38: =SUMPRODUCT((公告總庫!$N$9:$N$4019=$A38)*(YEAR(公告總庫!$D$9:$D$4019)=2016)) | G38: =SUMPRODUCT((公告總庫!$N$9:$N$4019=$A38)*(YEAR(公告總庫!$D$9:$D$4019)=2017)) | H38: =SUMPRODUCT((公告總庫!$N$9:$N$4019=$A38)*(YEAR(公告總庫!$D$9:$D$4019)=2018)) | I38: =SUMPRODUCT((公告總庫!$N$9:$N$4019=$A38)*(YEAR(公告總庫!$D$9:$D$4019)=2019)) | J38: =SUMPRODUCT((公告總庫!$N$9:$N$4019=$A38)*(YEAR(公告總庫!$D$9:$D$4019)=2020)) | K38: =SUMPRODUCT((公告總庫!$N$9:$N$4019=$A38)*(YEAR(公告總庫!$D$9:$D$4019)=2021)) | L38: =SUMPRODUCT((公告總庫!$N$9:$N$4019=$A38)*(YEAR(公告總庫!$D$9:$D$4019)=2022)) | M38: =SUMPRODUCT((公告總庫!$N$9:$N$4019=$A38)*(YEAR(公告總庫!$D$9:$D$4019)=2023)) | N38: =SUMPRODUCT((公告總庫!$N$9:$N$4019=$A38)*(YEAR(公告總庫!$D$9:$D$4019)=2024)) | O38: =SUMPRODUCT((公告總庫!$N$9:$N$4019=$A38)*(YEAR(公告總庫!$D$9:$D$4019)=2025)) | P38: =SUMPRODUCT((公告總庫!$N$9:$N$4019=$A38)*(YEAR(公告總庫!$D$9:$D$4019)=2026)) | Q38: =SUM(B38:P38)
A39: 黃寶輝 | B39: =SUMPRODUCT((公告總庫!$N$9:$N$4019=$A39)*(YEAR(公告總庫!$D$9:$D$4019)=2012)) | C39: =SUMPRODUCT((公告總庫!$N$9:$N$4019=$A39)*(YEAR(公告總庫!$D$9:$D$4019)=2013)) | D39: =SUMPRODUCT((公告總庫!$N$9:$N$4019=$A39)*(YEAR(公告總庫!$D$9:$D$4019)=2014)) | E39: =SUMPRODUCT((公告總庫!$N$9:$N$4019=$A39)*(YEAR(公告總庫!$D$9:$D$4019)=2015)) | F39: =SUMPRODUCT((公告總庫!$N$9:$N$4019=$A39)*(YEAR(公告總庫!$D$9:$D$4019)=2016)) | G39: =SUMPRODUCT((公告總庫!$N$9:$N$4019=$A39)*(YEAR(公告總庫!$D$9:$D$4019)=2017)) | H39: =SUMPRODUCT((公告總庫!$N$9:$N$4019=$A39)*(YEAR(公告總庫!$D$9:$D$4019)=2018)) | I39: =SUMPRODUCT((公告總庫!$N$9:$N$4019=$A39)*(YEAR(公告總庫!$D$9:$D$4019)=2019)) | J39: =SUMPRODUCT((公告總庫!$N$9:$N$4019=$A39)*(YEAR(公告總庫!$D$9:$D$4019)=2020)) | K39: =SUMPRODUCT((公告總庫!$N$9:$N$4019=$A39)*(YEAR(公告總庫!$D$9:$D$4019)=2021)) | L39: =SUMPRODUCT((公告總庫!$N$9:$N$4019=$A39)*(YEAR(公告總庫!$D$9:$D$4019)=2022)) | M39: =SUMPRODUCT((公告總庫!$N$9:$N$4019=$A39)*(YEAR(公告總庫!$D$9:$D$4019)=2023)) | N39: =SUMPRODUCT((公告總庫!$N$9:$N$4019=$A39)*(YEAR(公告總庫!$D$9:$D$4019)=2024)) | O39: =SUMPRODUCT((公告總庫!$N$9:$N$4019=$A39)*(YEAR(公告總庫!$D$9:$D$4019)=2025)) | P39: =SUMPRODUCT((公告總庫!$N$9:$N$4019=$A39)*(YEAR(公告總庫!$D$9:$D$4019)=2026)) | Q39: =SUM(B39:P39)
A40: 其他帳號 | B40: =SUMPRODUCT((YEAR(公告總庫!$D$9:$D$4019)=2012)*1)-SUM(B36:B39) | C40: =SUMPRODUCT((YEAR(公告總庫!$D$9:$D$4019)=2013)*1)-SUM(C36:C39) | D40: =SUMPRODUCT((YEAR(公告總庫!$D$9:$D$4019)=2014)*1)-SUM(D36:D39) | E40: =SUMPRODUCT((YEAR(公告總庫!$D$9:$D$4019)=2015)*1)-SUM(E36:E39) | F40: =SUMPRODUCT((YEAR(公告總庫!$D$9:$D$4019)=2016)*1)-SUM(F36:F39) | G40: =SUMPRODUCT((YEAR(公告總庫!$D$9:$D$4019)=2017)*1)-SUM(G36:G39) | H40: =SUMPRODUCT((YEAR(公告總庫!$D$9:$D$4019)=2018)*1)-SUM(H36:H39) | I40: =SUMPRODUCT((YEAR(公告總庫!$D$9:$D$4019)=2019)*1)-SUM(I36:I39) | J40: =SUMPRODUCT((YEAR(公告總庫!$D$9:$D$4019)=2020)*1)-SUM(J36:J39) | K40: =SUMPRODUCT((YEAR(公告總庫!$D$9:$D$4019)=2021)*1)-SUM(K36:K39) | L40: =SUMPRODUCT((YEAR(公告總庫!$D$9:$D$4019)=2022)*1)-SUM(L36:L39) | M40: =SUMPRODUCT((YEAR(公告總庫!$D$9:$D$4019)=2023)*1)-SUM(M36:M39) | N40: =SUMPRODUCT((YEAR(公告總庫!$D$9:$D$4019)=2024)*1)-SUM(N36:N39) | O40: =SUMPRODUCT((YEAR(公告總庫!$D$9:$D$4019)=2025)*1)-SUM(O36:O39) | P40: =SUMPRODUCT((YEAR(公告總庫!$D$9:$D$4019)=2026)*1)-SUM(P36:P39) | Q40: =SUM(B40:P40)
A41: 總計 | B41: =SUM(B36:B40) | C41: =SUM(C36:C40) | D41: =SUM(D36:D40) | E41: =SUM(E36:E40) | F41: =SUM(F36:F40) | G41: =SUM(G36:G40) | H41: =SUM(H36:H40) | I41: =SUM(I36:I40) | ... Q41: =SUM(Q36:Q40)
